{
  "originalCacheEntries": [
    {
      "key": "prov:4khdhub:movie:10131",
      "storedAt": 1757793766814,
      "meta": {
        "storedAt": 1757793766,
        "urlCount": 8,
        "ttlSeconds": 0
      },
      "data": {
        "success": true,
        "provider": "4khdhub",
        "type": "movie",
        "tmdbId": "10131",
        "imdbId": "tt0095742",
        "streams": [
          {
            "name": "4KHDHub - Pixeldrain - 2160p",
            "title": "Silver.and.the.Book.of.Dreams.2023.2160p.AMZN.WEB-DL.Hindi.DDP5.1-English.DDP5.1.H.265-4kHdHub.Com.mkv\n10.52 GB",
            "url": "https://pixeldrain.dev/api/file/qPdhYy9J?download",
            "quality": "2160p",
            "size": "10.52 GB",
            "fileName": "Silver.and.the.Book.of.Dreams.2023.2160p.AMZN.WEB-DL.Hindi.DDP5.1-English.DDP5.1.H.265-4kHdHub.Com.mkv",
            "type": "direct",
            "behaviorHints": {
              "bingeGroup": "4khdhub-streams"
            }
          },
          {
            "name": "4KHDHub - FSL Server - 2160p",
            "title": "Silver.and.the.Book.of.Dreams.2023.2160p.AMZN.WEB-DL.Hindi.DDP5.1-English.DDP5.1.H.265-4kHdHub.Com.mkv\n10.52 GB",
            "url": "https://fsl.fastcloud.casa/Silver.and.the.Book.of.Dreams.2023.2160p.AMZN.WEB-DL.Hindi.DDP5.1-English.DDP5.1.H.265-4kHdHub.Com.mkv?token=1757793765",
            "quality": "2160p",
            "size": "10.52 GB",
            "fileName": "Silver.and.the.Book.of.Dreams.2023.2160p.AMZN.WEB-DL.Hindi.DDP5.1-English.DDP5.1.H.265-4kHdHub.Com.mkv",
            "type": "direct",
            "behaviorHints": {
              "bingeGroup": "4khdhub-streams"
            }
          },
          {
            "name": "4KHDHub - Pixeldrain - 2160p",
            "title": "Silver.and.the.Book.of.Dreams.2023.2160p.AMZN.WEB-DL.Hindi.DDP5.1-English.DDP5.1.HDR.H.265-4kHdHub.Com.mkv\n10.48 GB",
            "url": "https://pixeldrain.dev/api/file/AEn1zySq?download",
            "quality": "2160p",
            "size": "10.48 GB",
            "fileName": "Silver.and.the.Book.of.Dreams.2023.2160p.AMZN.WEB-DL.Hindi.DDP5.1-English.DDP5.1.HDR.H.265-4kHdHub.Com.mkv",
            "type": "direct",
            "behaviorHints": {
              "bingeGroup": "4khdhub-streams"
            }
          },
          {
            "name": "4KHDHub - FSL Server - 2160p",
            "title": "Silver.and.the.Book.of.Dreams.2023.2160p.AMZN.WEB-DL.Hindi.DDP5.1-English.DDP5.1.HDR.H.265-4kHdHub.Com.mkv\n10.48 GB",
            "url": "https://fsl.fastcloud.casa/Silver.and.the.Book.of.Dreams.2023.2160p.AMZN.WEB-DL.Hindi.DDP5.1-English.DDP5.1.HDR.H.265-4kHdHub.Com.mkv?token=1757793765",
            "quality": "2160p",
            "size": "10.48 GB",
            "fileName": "Silver.and.the.Book.of.Dreams.2023.2160p.AMZN.WEB-DL.Hindi.DDP5.1-English.DDP5.1.HDR.H.265-4kHdHub.Com.mkv",
            "type": "direct",
            "behaviorHints": {
              "bingeGroup": "4khdhub-streams"
            }
          },
          {
            "name": "4KHDHub - Pixeldrain - 1080p",
            "title": "Silver.and.the.Book.of.Dreams.2023.1080p.AMZN.WEB-DL.Hindi.DDP5.1-English.DDP5.1.H.264-4kHdHub.Com.mkv\n5.63 GB",
            "url": "https://pixeldrain.dev/api/file/mzRvaEQD?download",
            "quality": "1080p",
            "size": "5.63 GB",
            "fileName": "Silver.and.the.Book.of.Dreams.2023.1080p.AMZN.WEB-DL.Hindi.DDP5.1-English.DDP5.1.H.264-4kHdHub.Com.mkv",
            "type": "direct",
            "behaviorHints": {
              "bingeGroup": "4khdhub-streams"
            }
          },
          {
            "name": "4KHDHub - FSL Server - 1080p",
            "title": "Silver.and.the.Book.of.Dreams.2023.1080p.AMZN.WEB-DL.Hindi.DDP5.1-English.DDP5.1.H.264-4kHdHub.Com.mkv\n5.63 GB",
            "url": "https://fsl.fastcloud.casa/Silver.and.the.Book.of.Dreams.2023.1080p.AMZN.WEB-DL.Hindi.DDP5.1-English.DDP5.1.H.264-4kHdHub.Com.mkv?token=1757793765",
            "quality": "1080p",
            "size": "5.63 GB",
            "fileName": "Silver.and.the.Book.of.Dreams.2023.1080p.AMZN.WEB-DL.Hindi.DDP5.1-English.DDP5.1.H.264-4kHdHub.Com.mkv",
            "type": "direct",
            "behaviorHints": {
              "bingeGroup": "4khdhub-streams"
            }
          },
          {
            "name": "4KHDHub - Pixeldrain - 1080p",
            "title": "Silver.and.the.Book.of.Dreams.2023.1080p.AMZN.WEB-DL.Hindi.DDP5.1-English.DDP5.1.H.265-4kHdHub.Com.mkv\n2.06 GB",
            "url": "https://pixeldrain.dev/api/file/J4RMeKXv?download",
            "quality": "1080p",
            "size": "2.06 GB",
            "fileName": "Silver.and.the.Book.of.Dreams.2023.1080p.AMZN.WEB-DL.Hindi.DDP5.1-English.DDP5.1.H.265-4kHdHub.Com.mkv",
            "type": "direct",
            "behaviorHints": {
              "bingeGroup": "4khdhub-streams"
            }
          },
          {
            "name": "4KHDHub - FSL Server - 1080p",
            "title": "Silver.and.the.Book.of.Dreams.2023.1080p.AMZN.WEB-DL.Hindi.DDP5.1-English.DDP5.1.H.265-4kHdHub.Com.mkv\n2.06 GB",
            "url": "https://fsl.fastcloud.casa/Silver.and.the.Book.of.Dreams.2023.1080p.AMZN.WEB-DL.Hindi.DDP5.1-English.DDP5.1.H.265-4kHdHub.Com.mkv?token=1757793765",
            "quality": "1080p",
            "size": "2.06 GB",
            "fileName": "Silver.and.the.Book.of.Dreams.2023.1080p.AMZN.WEB-DL.Hindi.DDP5.1-English.DDP5.1.H.265-4kHdHub.Com.mkv",
            "type": "direct",
            "behaviorHints": {
              "bingeGroup": "4khdhub-streams"
            }
          }
        ],
        "count": 8
      }
    },
    {
      "key": "prov:4khdhub:movie:1234603",
      "storedAt": 1757793715598,
      "meta": {
        "storedAt": 1757793715,
        "urlCount": 3,
        "ttlSeconds": 0
      },
      "data": {
        "success": true,
        "provider": "4khdhub",
        "type": "movie",
        "tmdbId": "1234603",
        "imdbId": "tt31015496",
        "streams": [
          {
            "name": "4KHDHub - Pixeldrain - 1080p",
            "title": "The Cable Guy 1996 1080p BluRay [Hindi DDP 5.1 + English DTS] x264 LoRD-LUMiX 4kHDHub.com.mkv\n13.58 GB",
            "url": "https://pixeldrain.dev/api/file/dCm6NH7J?download",
            "quality": "1080p",
            "size": "13.58 GB",
            "fileName": "The Cable Guy 1996 1080p BluRay [Hindi DDP 5.1 + English DTS] x264 LoRD-LUMiX 4kHDHub.com.mkv",
            "type": "direct",
            "behaviorHints": {
              "bingeGroup": "4khdhub-streams"
            }
          },
          {
            "name": "4KHDHub - Pixeldrain - 1080p",
            "title": "The Cable Guy 1996 1080p BluRay 10bit HEVC [Hindi DDP 5.1 + English DDP 5.1] x265 BeiTa-LUMiX 4kHDHub.com.mkv\n9.11 GB",
            "url": "https://pixeldrain.dev/api/file/NXagJMnP?download",
            "quality": "1080p",
            "size": "9.11 GB",
            "fileName": "The Cable Guy 1996 1080p BluRay 10bit HEVC [Hindi DDP 5.1 + English DDP 5.1] x265 BeiTa-LUMiX 4kHDHub.com.mkv",
            "type": "direct",
            "behaviorHints": {
              "bingeGroup": "4khdhub-streams"
            }
          },
          {
            "name": "4KHDHub - Pixeldrain - 1080p",
            "title": "The Cable Guy 1996 Open Matte 1080p AMZN WEB-DL [Hindi DDP 5.1 + English DDP 5.1] x264 BLUBIRD-LUMiX 4kHDHub.com.mkv\n8.53 GB",
            "url": "https://pixeldrain.dev/api/file/MkCggR11?download",
            "quality": "1080p",
            "size": "8.53 GB",
            "fileName": "The Cable Guy 1996 Open Matte 1080p AMZN WEB-DL [Hindi DDP 5.1 + English DDP 5.1] x264 BLUBIRD-LUMiX 4kHDHub.com.mkv",
            "type": "direct",
            "behaviorHints": {
              "bingeGroup": "4khdhub-streams"
            }
          }
        ],
        "count": 3
      }
    },
    {
      "key": "prov:4khdhub:movie:1268",
      "storedAt": 1757793712709,
      "meta": {
        "storedAt": 1757793712,
        "urlCount": 3,
        "ttlSeconds": 0
      },
      "data": {
        "success": true,
        "provider": "4khdhub",
        "type": "movie",
        "tmdbId": "1268",
        "imdbId": "tt0453451",
        "streams": [
          {
            "name": "4KHDHub - HubCloud - 1080p",
            "title": "Last Holiday (2006) 1080p BluRay REMUX AVC [Hindi DDP 5.1 + English TrueHD 5.1] (decibeL-Ionicboy).mkv\n28.02 GB",
            "url": "https://icy-river-3bdb.terapiyo233.workers.dev/30fa410fd526a9016f2bf2ce916ba9578792fe803738e9b6e5120588f1df1bdf5faf5161ac6c8a4dafdfbc58a7de8e01::07e581209ea59ade082aa6909a2d3ae2/1397312997/Last%20Holiday%20(2006)%201080p%20BluRay%20REMUX%20AVC%20[Hindi%20DDP%205.1%20+%20English%20TrueHD%205.1]%20(decibeL-Ionicboy).mkv",
            "quality": "1080p",
            "size": "28.02 GB",
            "fileName": "Last Holiday (2006) 1080p BluRay REMUX AVC [Hindi DDP 5.1 + English TrueHD 5.1] (decibeL-Ionicboy).mkv",
            "type": "direct",
            "behaviorHints": {
              "bingeGroup": "4khdhub-streams"
            }
          },
          {
            "name": "4KHDHub - HubCloud - 1080p",
            "title": "Last Holiday (2006) 1080p BluRay [Hindi DDP 5.1 + English DTS 5.1] x264 (playHD-Ionicboy)\n17.86 GB",
            "url": "https://royal-cell-f5d4.terapiyo2254127.workers.dev/55cc501bd5de52aa92c81922d58d5a5d475bfa40db365cd416ac4a3480ab48061747274a91ae027a54cc941499a3e84e::86f77298e4c8bd3892408ba6badf29f6/1397312997/Last%20Holiday%20(2006)%201080p%20BluRay%20[Hindi%20DDP%205.1%20+%20English%20DTS%205.1]%20x264%20(playHD-Ionicboy).mkv",
            "quality": "1080p",
            "size": "17.86 GB",
            "fileName": "Last Holiday (2006) 1080p BluRay [Hindi DDP 5.1 + English DTS 5.1] x264 (playHD-Ionicboy)",
            "type": "direct",
            "behaviorHints": {
              "bingeGroup": "4khdhub-streams"
            }
          },
          {
            "name": "4KHDHub - Pixeldrain - 1080p",
            "title": "Last Holiday 2006 1080p BluRay 10bit HEVC [Hindi DDP 5.1 + English DTS 5.1] x265 LEGi0N-Ionicboy.mkv\n5.46 GB",
            "url": "https://pixeldrain.dev/api/file/QmsdiSBq?download",
            "quality": "1080p",
            "size": "5.46 GB",
            "fileName": "Last Holiday 2006 1080p BluRay 10bit HEVC [Hindi DDP 5.1 + English DTS 5.1] x265 LEGi0N-Ionicboy.mkv",
            "type": "direct",
            "behaviorHints": {
              "bingeGroup": "4khdhub-streams"
            }
          }
        ],
        "count": 3
      }
    },
    {
      "key": "prov:dahmermovies:movie:13002",
      "storedAt": 1757793693319,
      "meta": {
        "storedAt": 1757793693,
        "urlCount": 1,
        "ttlSeconds": 0
      },
      "data": {
        "success": true,
        "provider": "dahmermovies",
        "type": "movie",
        "tmdbId": "13002",
        "imdbId": "tt0859594",
        "streams": [
          {
            "name": "DahmerMovies",
            "title": "DahmerMovies WEB-DL Upscale 8bit EAC3 5 1 x264-iVy",
            "url": "https://a.111477.xyz/movies/Barbie%20in%20the%2012%20Dancing%20Princesses%20(2006)/Barbie.In.The.12.Dancing.Princesses.2006.1080p.WEB-DL.Upscale.8bit.EAC3.5.1.x264-iVy.mp4",
            "quality": "1080p",
            "size": null,
            "type": "direct",
            "filename": "Barbie.In.The.12.Dancing.Princesses.2006.1080p.WEB-DL.Upscale.8bit.EAC3.5.1.x264-iVy.mp4"
          }
        ],
        "count": 1
      }
    },
    {
      "key": "prov:4khdhub:movie:2613",
      "storedAt": 1757793761729,
      "meta": {
        "storedAt": 1757793761,
        "urlCount": 8,
        "ttlSeconds": 0
      },
      "data": {
        "success": true,
        "provider": "4khdhub",
        "type": "movie",
        "tmdbId": "2613",
        "imdbId": "tt0105165",
        "streams": [
          {
            "name": "4KHDHub - FSL Server - 1080p",
            "title": "The Karate Kid 2010 REMASTERED 1080p BluRay REMUX AVC [Hindi-Tamil BD 5.1 640 Kbps + Telugu SONY DDP 2.0 128 Kbps + English DTS-HD MA 5.1] x264 playBD-LUMiX 4kHDHub.Com.mkv\n37.38 GB",
            "url": "https://fsl.fastcloud.casa/The%20Karate%20Kid%202010%20REMASTERED%201080p%20BluRay%20REMUX%20AVC%20[Hindi-Tamil%20BD%205.1%20640%20Kbps%20+%20Telugu%20SONY%20DDP%202.0%20128%20Kbps%20+%20English%20DTS-HD%20MA%205.1]%20x264%20playBD-LUMiX%204kHDHub.Com.mkv?token=1757793760",
            "quality": "1080p",
            "size": "37.38 GB",
            "fileName": "The Karate Kid 2010 REMASTERED 1080p BluRay REMUX AVC [Hindi-Tamil BD 5.1 640 Kbps + Telugu SONY DDP 2.0 128 Kbps + English DTS-HD MA 5.1] x264 playBD-LUMiX 4kHDHub.Com.mkv",
            "type": "direct",
            "behaviorHints": {
              "bingeGroup": "4khdhub-streams"
            }
          },
          {
            "name": "4KHDHub - FSL Server - 1080p",
            "title": "The Karate Kid 2010 1080p BluRay [Hindi-Tamil BD 5.1 640 Kbps + Telugu SONY DDP 2.0 128 Kbps + English DTS] x264 TayTO-LUMiX 4kHDHub.Com.mkv\n21.99 GB",
            "url": "https://fsl.fastcloud.casa/The%20Karate%20Kid%202010%201080p%20BluRay%20[Hindi-Tamil%20BD%205.1%20640%20Kbps%20+%20Telugu%20SONY%20DDP%202.0%20128%20Kbps%20+%20English%20DTS]%20x264%20TayTO-LUMiX%204kHDHub.Com.mkv?token=1757793760",
            "quality": "1080p",
            "size": "21.99 GB",
            "fileName": "The Karate Kid 2010 1080p BluRay [Hindi-Tamil BD 5.1 640 Kbps + Telugu SONY DDP 2.0 128 Kbps + English DTS] x264 TayTO-LUMiX 4kHDHub.Com.mkv",
            "type": "direct",
            "behaviorHints": {
              "bingeGroup": "4khdhub-streams"
            }
          },
          {
            "name": "4KHDHub - Pixeldrain - 2160p",
            "title": "The Karate Kid 2010 2160p AMZN WEB-DL SDR 10bit HEVC [Hindi-Tamil BD 5.1 640 Kbps + Telugu SONY DDP 2.0 128 Kbps + English DTS-HD MA 5.1] x265 FLAME-LUMiX 4kHDHub.Com.mkv\n15.27 GB",
            "url": "https://pixeldrain.dev/api/file/XFUvsXrr?download",
            "quality": "2160p",
            "size": "15.27 GB",
            "fileName": "The Karate Kid 2010 2160p AMZN WEB-DL SDR 10bit HEVC [Hindi-Tamil BD 5.1 640 Kbps + Telugu SONY DDP 2.0 128 Kbps + English DTS-HD MA 5.1] x265 FLAME-LUMiX 4kHDHub.Com.mkv",
            "type": "direct",
            "behaviorHints": {
              "bingeGroup": "4khdhub-streams"
            }
          },
          {
            "name": "4KHDHub - FSL Server - 2160p",
            "title": "The Karate Kid 2010 2160p AMZN WEB-DL SDR 10bit HEVC [Hindi-Tamil BD 5.1 640 Kbps + Telugu SONY DDP 2.0 128 Kbps + English DTS-HD MA 5.1] x265 FLAME-LUMiX 4kHDHub.Com.mkv\n15.27 GB",
            "url": "https://fsl.fastcloud.casa/The%20Karate%20Kid%202010%202160p%20AMZN%20WEB-DL%20SDR%2010bit%20HEVC%20[Hindi-Tamil%20BD%205.1%20640%20Kbps%20+%20Telugu%20SONY%20DDP%202.0%20128%20Kbps%20+%20English%20DTS-HD%20MA%205.1]%20x265%20FLAME-LUMiX%204kHDHub.Com.mkv?token=1757793760",
            "quality": "2160p",
            "size": "15.27 GB",
            "fileName": "The Karate Kid 2010 2160p AMZN WEB-DL SDR 10bit HEVC [Hindi-Tamil BD 5.1 640 Kbps + Telugu SONY DDP 2.0 128 Kbps + English DTS-HD MA 5.1] x265 FLAME-LUMiX 4kHDHub.Com.mkv",
            "type": "direct",
            "behaviorHints": {
              "bingeGroup": "4khdhub-streams"
            }
          },
          {
            "name": "4KHDHub - Pixeldrain - 2160p",
            "title": "The Karate Kid 2010 2160p WEBRip SDR 10bit HEVC [Hindi-Tamil BD 5.1 640 Kbps + Telugu SONY DDP 2.0 128 Kbps + English DDP 5.1] x265 YTS-LUMiX 4kHDHub.Com.mkv\n7.87 GB",
            "url": "https://pixeldrain.dev/api/file/ewpYqMD8?download",
            "quality": "2160p",
            "size": "7.87 GB",
            "fileName": "The Karate Kid 2010 2160p WEBRip SDR 10bit HEVC [Hindi-Tamil BD 5.1 640 Kbps + Telugu SONY DDP 2.0 128 Kbps + English DDP 5.1] x265 YTS-LUMiX 4kHDHub.Com.mkv",
            "type": "direct",
            "behaviorHints": {
              "bingeGroup": "4khdhub-streams"
            }
          },
          {
            "name": "4KHDHub - FSL Server - 2160p",
            "title": "The Karate Kid 2010 2160p WEBRip SDR 10bit HEVC [Hindi-Tamil BD 5.1 640 Kbps + Telugu SONY DDP 2.0 128 Kbps + English DDP 5.1] x265 YTS-LUMiX 4kHDHub.Com.mkv\n7.87 GB",
            "url": "https://pub-52f57cc1b81f4ecdac02802c1566c33d.r2.dev/The%20Karate%20Kid%202010%202160p%20WEBRip%20SDR%2010bit%20HEVC%20[Hindi-Tamil%20BD%205.1%20640%20Kbps%20+%20Telugu%20SONY%20DDP%202.0%20128%20Kbps%20+%20English%20DDP%205.1]%20x265%20YTS-LUMiX%204kHDHub.Com.mkv?token=1757793760",
            "quality": "2160p",
            "size": "7.87 GB",
            "fileName": "The Karate Kid 2010 2160p WEBRip SDR 10bit HEVC [Hindi-Tamil BD 5.1 640 Kbps + Telugu SONY DDP 2.0 128 Kbps + English DDP 5.1] x265 YTS-LUMiX 4kHDHub.Com.mkv",
            "type": "direct",
            "behaviorHints": {
              "bingeGroup": "4khdhub-streams"
            }
          },
          {
            "name": "4KHDHub - Pixeldrain - 1080p",
            "title": "The Karate Kid 2010 RM4K 1080p BluRay 10bit HEVC [Hindi-Tamil BD 5.1 640 Kbps + Telugu SONY DDP 2.0 128 Kbps + English AAC 5.1] x265 Tigole-LUMiX 4kHDHub.Com.mkv\n7.7 GB",
            "url": "https://pixeldrain.dev/api/file/KYYCRtH1?download",
            "quality": "1080p",
            "size": "7.7 GB",
            "fileName": "The Karate Kid 2010 RM4K 1080p BluRay 10bit HEVC [Hindi-Tamil BD 5.1 640 Kbps + Telugu SONY DDP 2.0 128 Kbps + English AAC 5.1] x265 Tigole-LUMiX 4kHDHub.Com.mkv",
            "type": "direct",
            "behaviorHints": {
              "bingeGroup": "4khdhub-streams"
            }
          },
          {
            "name": "4KHDHub - FSL Server - 1080p",
            "title": "The Karate Kid 2010 RM4K 1080p BluRay 10bit HEVC [Hindi-Tamil BD 5.1 640 Kbps + Telugu SONY DDP 2.0 128 Kbps + English AAC 5.1] x265 Tigole-LUMiX 4kHDHub.Com.mkv\n7.7 GB",
            "url": "https://fsl.fastcloud.casa/The%20Karate%20Kid%202010%20RM4K%201080p%20BluRay%2010bit%20HEVC%20[Hindi-Tamil%20BD%205.1%20640%20Kbps%20+%20Telugu%20SONY%20DDP%202.0%20128%20Kbps%20+%20English%20AAC%205.1]%20x265%20Tigole-LUMiX%204kHDHub.Com.mkv?token=1757793760",
            "quality": "1080p",
            "size": "7.7 GB",
            "fileName": "The Karate Kid 2010 RM4K 1080p BluRay 10bit HEVC [Hindi-Tamil BD 5.1 640 Kbps + Telugu SONY DDP 2.0 128 Kbps + English AAC 5.1] x265 Tigole-LUMiX 4kHDHub.Com.mkv",
            "type": "direct",
            "behaviorHints": {
              "bingeGroup": "4khdhub-streams"
            }
          }
        ],
        "count": 8
      }
    },
    {
      "key": "prov:moviesmod:movie:2613",
      "storedAt": 1757793766904,
      "meta": {
        "storedAt": 1757793766,
        "urlCount": 1,
        "ttlSeconds": 0
      },
      "data": {
        "success": true,
        "provider": "moviesmod",
        "type": "movie",
        "tmdbId": "2613",
        "imdbId": "tt0105165",
        "streams": [
          {
            "name": "MoviesMod",
            "title": "Prelude to a Kiss 1992 720p Moviesmod org\n750.73MB",
            "url": "https://video-downloads.googleusercontent.com/ADGPM2nrnsvp9tOc2CLIJK714Syn8_ZW48c5jANruaHUwe5H64jtzdm9nIexrqs9kiwUctnt-L0dwnYBScbdFp5cz8zxsgwxySZc4qEP-bQAeU6__EnNKrpCPk3UZbnh9_C66Hkhkxd7NgtgMkbqY1cxzOFsciHaR2nyTJlIOnhI2vXaCslXlP2HRIab9HZBAPQq3qm9iIFpbR6xc6rF4sxQ6VQf_IMWnBr3Wt1cmCv2CRtikUD8HwlAyeTpCYESj3GDdFt5LM810XUftHU06c3ifCXzUvmxxeZdbF1McAemoTmzADGIo3aCy9o8Tc7pv2bkNdpXA7RVJl3t5IUSpG5V1WY4BTn9NZ-WIYBwjbtjPEn-5CiVSyh-HPtGT6V62i52Wy4x3p_ecIRkSQcvlJ8EaDtkRpqyw7kPLcUD3Zsqi_H26qSLE8kr_mwsHndDIl6ukfyl9rOOn-hOqjFBEC0s5aUmTqgVqlpd8ONIIs3u1CM1j9p8TpcssfFDF1XfJ-3kn-hDfaf-2X0rGXC81GbPUBbmMT_tr56V9veamDvCE1xvX_JNM6oS9tYoE-xrp8IOrZfDmyIVo0DbSkw59ScHlII_0OLFsoZ6g18YfsoTiQysw1VEpr63k_JRHrUlCkq-5GB_E-UFIuuUv2xEdd7n-pOjE7OYzxoIcbaxhT5QZuYlFn_t_S5IfHEQ1jOktZs2zYkX9iz2zouFF9Y6CBrJkhHpKtq14-GwAFCAT32FuZgkfExhw4ALCp1fPNePG72YJmYRyOQ4bhX1XRreSPtdFqExxr-XAzi5RQgcMeoRFrVsw9xv2kEviL41k8CRxEJ_PbYBUKrH74JbvGP45vt9G0vPQr_tFGshqAxcXdXcpWs-NiynFDAmw10rD2zY0LoiYNajFlVquJwZqb1rXuH6Mw7Fv29pFPNgIwzEAAt8PAO4g4RSbm4p0s3gymB5LCyM58HaoUQK7JZ67GyTOB0XnCjlpDnEwhj9BaaOdlplTBCyN3atqKM9LuEP0V4XlsmVZ3C0qTpzJLGMvdvRejMnEYJoHYhak2olf-dieHdiTYKdCb9JawY",
            "quality": "720p",
            "size": "750.73MB",
            "fileName": "Prelude.to.a.Kiss.1992.720p.Moviesmod.org.mkv",
            "type": "direct"
          }
        ],
        "count": 1
      }
    },
    {
      "key": "prov:4khdhub:movie:351523",
      "storedAt": 1757793717352,
      "meta": {
        "storedAt": 1757793717,
        "urlCount": 5,
        "ttlSeconds": 0
      },
      "data": {
        "success": true,
        "provider": "4khdhub",
        "type": "movie",
        "tmdbId": "351523",
        "imdbId": "tt5987506",
        "streams": [
          {
            "name": "4KHDHub - FSL Server - 1080p",
            "title": "American Reunion 2012 UNRATED 1080p BluRay REMUX x264 AVC [Org NF Hindi DDP 5.1 - 640Kbps + English DTS-HDMA 5.1] ESub - FraMeSToR-4KHDHub.mkv\n19.02 GB",
            "url": "https://pub-52f57cc1b81f4ecdac02802c1566c33d.r2.dev/American%20Reunion%202012%20UNRATED%201080p%20BluRay%20REMUX%20x264%20AVC%20[Org%20NF%20Hindi%20DDP%205.1%20-%20640Kbps%20+%20English%20DTS-HDMA%205.1]%20ESub%20-%20FraMeSToR-4KHDHub.mkv?token=1757793716",
            "quality": "1080p",
            "size": "19.02 GB",
            "fileName": "American Reunion 2012 UNRATED 1080p BluRay REMUX x264 AVC [Org NF Hindi DDP 5.1 - 640Kbps + English DTS-HDMA 5.1] ESub - FraMeSToR-4KHDHub.mkv",
            "type": "direct",
            "behaviorHints": {
              "bingeGroup": "4khdhub-streams"
            }
          },
          {
            "name": "4KHDHub - Pixeldrain - 1080p",
            "title": "American Reunion 2012 UNRATED 1080p BluRay x264 AVC [Org NF Hindi DDP 5.1 - 640Kbps + English DTS-HDMA 5.1] ESub - CtrlHD-4KHDHub.mkv\n15.63 GB",
            "url": "https://pixeldrain.dev/api/file/jGdFRNP9?download",
            "quality": "1080p",
            "size": "15.63 GB",
            "fileName": "American Reunion 2012 UNRATED 1080p BluRay x264 AVC [Org NF Hindi DDP 5.1 - 640Kbps + English DTS-HDMA 5.1] ESub - CtrlHD-4KHDHub.mkv",
            "type": "direct",
            "behaviorHints": {
              "bingeGroup": "4khdhub-streams"
            }
          },
          {
            "name": "4KHDHub - FSL Server - 1080p",
            "title": "American Reunion 2012 UNRATED 1080p BluRay x264 AVC [Org NF Hindi DDP 5.1 - 640Kbps + English DTS-HDMA 5.1] ESub - CtrlHD-4KHDHub.mkv\n15.63 GB",
            "url": "https://pub-52f57cc1b81f4ecdac02802c1566c33d.r2.dev/American%20Reunion%202012%20UNRATED%201080p%20BluRay%20x264%20AVC%20[Org%20NF%20Hindi%20DDP%205.1%20-%20640Kbps%20+%20English%20DTS-HDMA%205.1]%20ESub%20-%20CtrlHD-4KHDHub.mkv?token=1757793716",
            "quality": "1080p",
            "size": "15.63 GB",
            "fileName": "American Reunion 2012 UNRATED 1080p BluRay x264 AVC [Org NF Hindi DDP 5.1 - 640Kbps + English DTS-HDMA 5.1] ESub - CtrlHD-4KHDHub.mkv",
            "type": "direct",
            "behaviorHints": {
              "bingeGroup": "4khdhub-streams"
            }
          },
          {
            "name": "4KHDHub - Pixeldrain - 1080p",
            "title": "American Reunion 2012 UNRATED 1080p 10bit BluRay x265 HEVC [Org NF Hindi DDP 5.1 - 640Kbps + English AAC 5.1] ESub - FreetheFish-4KHDHub.mkv\n5.46 GB",
            "url": "https://pixeldrain.dev/api/file/S4YD4MVc?download",
            "quality": "1080p",
            "size": "5.46 GB",
            "fileName": "American Reunion 2012 UNRATED 1080p 10bit BluRay x265 HEVC [Org NF Hindi DDP 5.1 - 640Kbps + English AAC 5.1] ESub - FreetheFish-4KHDHub.mkv",
            "type": "direct",
            "behaviorHints": {
              "bingeGroup": "4khdhub-streams"
            }
          },
          {
            "name": "4KHDHub - FSL Server - 1080p",
            "title": "American Reunion 2012 UNRATED 1080p 10bit BluRay x265 HEVC [Org NF Hindi DDP 5.1 - 640Kbps + English AAC 5.1] ESub - FreetheFish-4KHDHub.mkv\n5.46 GB",
            "url": "https://pub-52f57cc1b81f4ecdac02802c1566c33d.r2.dev/American%20Reunion%202012%20UNRATED%201080p%2010bit%20BluRay%20x265%20HEVC%20[Org%20NF%20Hindi%20DDP%205.1%20-%20640Kbps%20+%20English%20AAC%205.1]%20ESub%20-%20FreetheFish-4KHDHub.mkv?token=1757793716",
            "quality": "1080p",
            "size": "5.46 GB",
            "fileName": "American Reunion 2012 UNRATED 1080p 10bit BluRay x265 HEVC [Org NF Hindi DDP 5.1 - 640Kbps + English AAC 5.1] ESub - FreetheFish-4KHDHub.mkv",
            "type": "direct",
            "behaviorHints": {
              "bingeGroup": "4khdhub-streams"
            }
          }
        ],
        "count": 5
      }
    },
    {
      "key": "prov:4khdhub:movie:38101",
      "storedAt": 1757793759580,
      "meta": {
        "storedAt": 1757793759,
        "urlCount": 8,
        "ttlSeconds": 0
      },
      "data": {
        "success": true,
        "provider": "4khdhub",
        "type": "movie",
        "tmdbId": "38101",
        "imdbId": "tt0026934",
        "streams": [
          {
            "name": "4KHDHub - Pixeldrain - 2160p",
            "title": "Thirteen.Lives.2022.2160p.AMZN.WEB-DL.Hindi.DDP5.1-English.DDP5.1.H.265-4kHdHub.Com.mkv\n16.71 GB",
            "url": "https://pixeldrain.dev/api/file/GWzhD7Fg?download",
            "quality": "2160p",
            "size": "16.71 GB",
            "fileName": "Thirteen.Lives.2022.2160p.AMZN.WEB-DL.Hindi.DDP5.1-English.DDP5.1.H.265-4kHdHub.Com.mkv",
            "type": "direct",
            "behaviorHints": {
              "bingeGroup": "4khdhub-streams"
            }
          },
          {
            "name": "4KHDHub - FSL Server - 2160p",
            "title": "Thirteen.Lives.2022.2160p.AMZN.WEB-DL.Hindi.DDP5.1-English.DDP5.1.H.265-4kHdHub.Com.mkv\n16.71 GB",
            "url": "https://fsl.fastcloud.casa/Thirteen.Lives.2022.2160p.AMZN.WEB-DL.Hindi.DDP5.1-English.DDP5.1.H.265-4kHdHub.Com.mkv?token=1757789901",
            "quality": "2160p",
            "size": "16.71 GB",
            "fileName": "Thirteen.Lives.2022.2160p.AMZN.WEB-DL.Hindi.DDP5.1-English.DDP5.1.H.265-4kHdHub.Com.mkv",
            "type": "direct",
            "behaviorHints": {
              "bingeGroup": "4khdhub-streams"
            }
          },
          {
            "name": "4KHDHub - Pixeldrain - 2160p",
            "title": "Thirteen.Lives.2022.2160p.AMZN.WEB-DL.Hindi.DDP5.1-English.DDP5.1.HDR.H.265-4kHdHub.Com.mkv\n16.43 GB",
            "url": "https://pixeldrain.dev/api/file/qaiNDdUa?download",
            "quality": "2160p",
            "size": "16.43 GB",
            "fileName": "Thirteen.Lives.2022.2160p.AMZN.WEB-DL.Hindi.DDP5.1-English.DDP5.1.HDR.H.265-4kHdHub.Com.mkv",
            "type": "direct",
            "behaviorHints": {
              "bingeGroup": "4khdhub-streams"
            }
          },
          {
            "name": "4KHDHub - FSL Server - 2160p",
            "title": "Thirteen.Lives.2022.2160p.AMZN.WEB-DL.Hindi.DDP5.1-English.DDP5.1.HDR.H.265-4kHdHub.Com.mkv\n16.43 GB",
            "url": "https://fsl.fastcloud.casa/Thirteen.Lives.2022.2160p.AMZN.WEB-DL.Hindi.DDP5.1-English.DDP5.1.HDR.H.265-4kHdHub.Com.mkv?token=1757792803",
            "quality": "2160p",
            "size": "16.43 GB",
            "fileName": "Thirteen.Lives.2022.2160p.AMZN.WEB-DL.Hindi.DDP5.1-English.DDP5.1.HDR.H.265-4kHdHub.Com.mkv",
            "type": "direct",
            "behaviorHints": {
              "bingeGroup": "4khdhub-streams"
            }
          },
          {
            "name": "4KHDHub - Pixeldrain - 1080p",
            "title": "Thirteen.Lives.2022.1080p.AMZN.WEB-DL.Hindi.DDP5.1-English.DDP5.1.H.264-4kHdHub.Com.mkv\n9.62 GB",
            "url": "https://pixeldrain.dev/api/file/kh9BXjjt?download",
            "quality": "1080p",
            "size": "9.62 GB",
            "fileName": "Thirteen.Lives.2022.1080p.AMZN.WEB-DL.Hindi.DDP5.1-English.DDP5.1.H.264-4kHdHub.Com.mkv",
            "type": "direct",
            "behaviorHints": {
              "bingeGroup": "4khdhub-streams"
            }
          },
          {
            "name": "4KHDHub - FSL Server - 1080p",
            "title": "Thirteen.Lives.2022.1080p.AMZN.WEB-DL.Hindi.DDP5.1-English.DDP5.1.H.264-4kHdHub.Com.mkv\n9.62 GB",
            "url": "https://fsl.fastcloud.casa/Thirteen.Lives.2022.1080p.AMZN.WEB-DL.Hindi.DDP5.1-English.DDP5.1.H.264-4kHdHub.Com.mkv?token=1757792803",
            "quality": "1080p",
            "size": "9.62 GB",
            "fileName": "Thirteen.Lives.2022.1080p.AMZN.WEB-DL.Hindi.DDP5.1-English.DDP5.1.H.264-4kHdHub.Com.mkv",
            "type": "direct",
            "behaviorHints": {
              "bingeGroup": "4khdhub-streams"
            }
          },
          {
            "name": "4KHDHub - Pixeldrain - 1080p",
            "title": "Thirteen.Lives.2022.1080p.AMZN.WEB-DL.Hindi.DDP5.1-English.DDP5.1.H.265-4kHdHub.Com.mkv\n4.64 GB",
            "url": "https://pixeldrain.dev/api/file/uYvrAeAg?download",
            "quality": "1080p",
            "size": "4.64 GB",
            "fileName": "Thirteen.Lives.2022.1080p.AMZN.WEB-DL.Hindi.DDP5.1-English.DDP5.1.H.265-4kHdHub.Com.mkv",
            "type": "direct",
            "behaviorHints": {
              "bingeGroup": "4khdhub-streams"
            }
          },
          {
            "name": "4KHDHub - FSL Server - 1080p",
            "title": "Thirteen.Lives.2022.1080p.AMZN.WEB-DL.Hindi.DDP5.1-English.DDP5.1.H.265-4kHdHub.Com.mkv\n4.64 GB",
            "url": "https://fsl.fastcloud.casa/Thirteen.Lives.2022.1080p.AMZN.WEB-DL.Hindi.DDP5.1-English.DDP5.1.H.265-4kHdHub.Com.mkv?token=1757792803",
            "quality": "1080p",
            "size": "4.64 GB",
            "fileName": "Thirteen.Lives.2022.1080p.AMZN.WEB-DL.Hindi.DDP5.1-English.DDP5.1.H.265-4kHdHub.Com.mkv",
            "type": "direct",
            "behaviorHints": {
              "bingeGroup": "4khdhub-streams"
            }
          }
        ],
        "count": 8
      }
    },
    {
      "key": "prov:moviesmod:movie:902",
      "storedAt": 1757793701725,
      "meta": {
        "storedAt": 1757793701,
        "urlCount": 2,
        "ttlSeconds": 0
      },
      "data": {
        "success": true,
        "provider": "moviesmod",
        "type": "movie",
        "tmdbId": "902",
        "imdbId": "tt0112682",
        "streams": [
          {
            "name": "MoviesMod",
            "title": "The City of Lost Children 1995 1080p Moviesmod org\n2.92GB",
            "url": "https://video-downloads.googleusercontent.com/ADGPM2lHFt6ZE1gp1UuA6fY31zzhGDVVH1AMCe2f5nOc87qO9fiXmvMjH8Vga6FG4OS8WdeyOGB1FjO6hqRNmNDvFh6UVoMLOnzanijltxPA6xHmHdYqnkbPEgNBReqHEURRW71aUQXIqu8HHB_NIJuJ8oa4FNbPX41jeNF3L1EfflxICpZJz0cx-Lh2T8djG5m9fE2pIL2eeSis-pRT3TcqqI2xiwc8dLlqf_Yg6zKoHFH0c1przHFfVqbhdE1PTwqh0h_YjzH0YRrlHdSVwQJEf-VZpPyh8rzEOBMdwzGXOErKYbP_KvEuGHNOkRduj3xadgSSmOCV0jm3ASIIn9DG4pXRic609R5PzySSd55julUHh3uG6CreR90Qp8uX8O-pqT1fGGk8Q-rpeqXt2x92xyzreDg_rmqJQL1-ilIO4O5QZcxQUPsPgCexKJccvwLmrF74K0OAyzua-EXY8mHayDbv6PhAQWyySSHFbJB1ZwnRXplhB2gSM0txHDcf77758-1tBmVsIS0zQ2Uc-VsMvxN7sR4st9hPQQmHOQjrBrpyG-MbbE3ocs0EDffgW1jp82GXJNm-aoW-Ms4fANz2AlFRio78T_OZEVevZH58a_KwXPBFMUNB6hnDe1wzSlJ89aVytBx3Oo1EqC2A7HjrXKKzFUgE86X1Lar6i-xT81aSzNdByN-P1eZowrrDi4mzF_Pch3Qg1ygFKqKICuWla_s9nUKiNh7mMFQg0snqQZE-JhwPlRBPopfvGOgjDhP1WllGfCl3RMOMxXJeEFbB0py_5TLbTeVHLe8WYg6xxtg85zC84_gJdKCexETu3950dcU6v91zLIt-bK1CBraKqDW_OEkr9GnmQvLBPmtNjyaB-s1i5Kx6Kn2pKb8U8Pznl2AWh2M9MZxdcHBhQyBE_o2ML3V4p9HwfAce2Hb1E8L2Xp-KUO0fvTBQT8gj9sgfQWw9p7tFp8JFu9257J9iEIBasTBiss7C7KT_w721ACWpehnI0xBwDeF1YBIVX5Qv5t-C2FxgU7kYnPqoXeJf2V0Uy4deXGjvRJyaxplLu4CtCd3Moq0",
            "quality": "1080p",
            "size": "2.92GB",
            "fileName": "The.City.of.Lost.Children.1995.1080p.Moviesmod.org.mkv",
            "type": "direct"
          },
          {
            "name": "MoviesMod",
            "title": "The City of Lost Children 1995 720p Moviesmod org\n899.96MB",
            "url": "https://video-downloads.googleusercontent.com/ADGPM2n94bbjPwdkb02CuwiB5MUrawrGrK2yZVKahFcrWPphabGtG0zEIzE6JEFloE5y8gwKGvHAtXzfUrmTgL5QuR043mBXxys5Ny9f9Tpq2ak7v47GLkTPGEbHXcIM7WDRjmuReSEjDdQAz0JUR5w6VoEvLgGPIB_OPG67Eo8IopS9GiyIAERcyztaU83kcbo352BoSkM8qWR1JWJDWOY2iyldy-bVBAwSWPLRCryl_fa_oeJBbnCo5yxhlo_VuD3Z_nWspQn3wsIN_6vgBgHzrZGJDz24E7nbpwAC3e49s8a2QfR9fdHQ6y8sLooZBsUC20eugUAWUpA0TmKAV6Uu3dFSbzRrgeZfYBg-w2rGYsJ5vSRV_WEmp3dzOMkitj3ENOgLaFEGXxPRCGvO9YhIq7BPq2ITBzkdjsWjhJ5SJcIhSjrVw5j9g_GjH_XnLaOQRC7GrzMHIidGYgJWzyZiWYEFhWzRfBcNQi_kn43jY97y3-OuG6HUr4-_LQxaQv_Yk8GM_k8dkzPg6Fjgqd7-Hs_FqSa75xQJX3CVcbF1uRKAD1Xc1YLZyZqH9Us3-iesuoMRpF09Au3gzy3JtKXuQQPB05mIJyxym-8sKaDFjSosmCLehWcUMbAjhyVRlCztYpiyy_hZ1RPb5xD0-x02SvCd0LdxQkFYBWUEaG3ByghYMSyn4luTwkDhYVPpA9cmXQvecC8ChQCM8kOU4dQxigfy3uPpIWowuqYZKHj2XNiBmaPQ3PK_A75g7NqiVyWLklaU_7zOexjhrmQjsxgLPxjKu5-Wb0ybcJA-v66ljUznSjWwmjg8SQMV8ZRIs0d6_mn1d1X4M4w0OUdjm-_ue6c7kpZIIlPAtbtraKH5k7GXYt99nmGetOLttqMsMYBaqjvCeWKv_lJ-MVbVhSLS_y6_gaNoTvzxAlFev-T-obBjMX8xyE2Gcy1RFfDGPpMQmKVgg-VTNLh7Cx4YWkFF_n80_ixfHyNQxf0MrEAPiZDJ7Vp6wK1ebd8koq9uDADfTYZq5Sr7FWerCAGutHyyE6xAHWl44-3ToxB6-cn-fCnSI3ZjpTM",
            "quality": "720p",
            "size": "899.96MB",
            "fileName": "The.City.of.Lost.Children.1995.720p.Moviesmod.org.mkv",
            "type": "direct"
          }
        ],
        "count": 2
      }
    },
    {
      "key": "prov:dahmermovies:tv:1100:s4e1",
      "storedAt": 1757793748953,
      "meta": {
        "storedAt": 1757793748,
        "urlCount": 2,
        "ttlSeconds": 0
      },
      "data": {
        "success": true,
        "provider": "dahmermovies",
        "type": "tv",
        "tmdbId": "1100",
        "imdbId": "tt0460649",
        "season": 4,
        "episode": 1,
        "streams": [
          {
            "name": "DahmerMovies",
            "title": "DahmerMovies Remux][DTS-HD MA 5 1][AVC]-NOGRP",
            "url": "https://a.111477.xyz/tvs/How%20I%20Met%20Your%20Mother/Season%204/How%20I%20Met%20Your%20Mother%20(2005)%20-%20S04E01%20-%20Do%20I%20Know%20You%20[Bluray-1080p%20Remux][DTS-HD%20MA%205.1][AVC]-NOGRP.mkv",
            "quality": "1080p | REMUX",
            "size": null,
            "type": "direct",
            "filename": "How I Met Your Mother (2005) - S04E01 - Do I Know You [Bluray-1080p Remux][DTS-HD MA 5.1][AVC]-NOGRP.mkv"
          },
          {
            "name": "DahmerMovies",
            "title": "DahmerMovies ][EAC3 5 1][h264]-FLUX",
            "url": "https://a.111477.xyz/tvs/How%20I%20Met%20Your%20Mother/Season%204/How%20I%20Met%20Your%20Mother%20(2005)%20-%20S04E01%20-%20Do%20I%20Know%20You%20[WEBDL-1080p][EAC3%205.1][h264]-FLUX.mkv",
            "quality": "1080p",
            "size": null,
            "type": "direct",
            "filename": "How I Met Your Mother (2005) - S04E01 - Do I Know You [WEBDL-1080p][EAC3 5.1][h264]-FLUX.mkv"
          }
        ],
        "count": 2
      }
    },
    {
      "key": "prov:moviesmod:tv:1100:s4e1",
      "storedAt": 1757793747630,
      "meta": {
        "storedAt": 1757793747,
        "urlCount": 1,
        "ttlSeconds": 0
      },
      "data": {
        "success": true,
        "provider": "moviesmod",
        "type": "tv",
        "tmdbId": "1100",
        "imdbId": "tt0460649",
        "season": 4,
        "episode": 1,
        "streams": [
          {
            "name": "MoviesMod",
            "title": "How I Met Your Mother S04E01 1080p 10Bit BluRay English Esubs Moviesmod Net\n489.49MB • 10-bit",
            "url": "https://video-downloads.googleusercontent.com/ADGPM2mRkLz6qqbgfx7gsv60PrOXAiP07Wb-1G50fbte381XAUO3AOPBgM04WNCov60atLr31l1jfBaQVYRiBGTlOU1fqZRPyfvGW76WGSOrYL2yZ-H8QwLWxmjxCx5a9QZ2AU_6Ufm6-97Gl2IpiXJcl23MwHC_l0tIpDT9MHKSCZIUvWxibHm8h1REwXSvou3kbm3w-nVIokAT-9REfobEHWSEklrFd3s1-MOUL0MTdHuOXQ0l2ebUgl8t6YErqfud5bAFS__Q3zByGny9D9gHNJwSLIBVdpodSoLWpcwhMYokzy6ojFoG-t8LDHkxZXBNN0XFhtPf66nU978Laxlkiki_l8fM7aWLW8W81iw_stjJyeLWfHo7sQN5p5KX4bjXVF4lxjm7_zWSW130zist2eg7W9lvZuLUlIQVyMc4jM525re22cyolEJLadpRHnM1N0YXQDUACwtutUy6C9QaDt678-mhhS1QzZTHt33597WHsYc26F5YjQioGjTN-DgZd8NdpsxnCoE-DUUcOkICj9JcIYtlsO_T0uD2Q-K4giY5XsZq1aCvazxFFQNdScV7ovFbf4RYAjmDLpnklSANiiF7gv6NsNOwqB6ITu_xBSyki69tjJxP6jOEEfKVixrL_w5nr9edeTpLZteGnkBiFLqgEaW_Zbw5UsCaordwQnzMvP_o3O2yAlcW1aqyH101ot3M9LsNetee7OWE8LxBRMQXuOVr4gWvWDLXHlzw1XzYv4NgUrY-Pdp2C81diNI9xsH18jdJR7foPn_4ZfOmrMzFA_tln8TS3mlWv9tdl0yU-ELxyBOwlOkI2qyY6NTmRg9qAwQk4GKVmrYza6uTrCEylB_D6qewxxTmYFxQZaNkpHKL-VJzZgMP8CfhFsSWdrfx0qv-F1QIR7JDlRNcWtMGYg1CLKmT22SFGaXczNYggizvj2KJ1RQPiVdLgw9Gv3Qi7vNE6unUA-DuTx6P2tMfjIJb7SFC4AAm1YyyHqg2Y8Sf9a5_2rfS-X71vBkSzrNvWTGP9Ja3i1KtU0pF2C_ens2jvCl50u_isiF294BX-QHU3F4",
            "quality": "1080p",
            "size": "489.49MB",
            "fileName": "How.I.Met.Your.Mother.S04E01.1080p.10Bit.BluRay.English.Esubs.Moviesmod.Net.mkv",
            "type": "direct"
          }
        ],
        "count": 1
      }
    },
    {
      "key": "prov:dahmermovies:tv:1100:s4e13",
      "storedAt": 1757793757784,
      "meta": {
        "storedAt": 1757793757,
        "urlCount": 2,
        "ttlSeconds": 0
      },
      "data": {
        "success": true,
        "provider": "dahmermovies",
        "type": "tv",
        "tmdbId": "1100",
        "imdbId": "tt0460649",
        "season": 4,
        "episode": 13,
        "streams": [
          {
            "name": "DahmerMovies",
            "title": "DahmerMovies Remux][DTS-HD MA 5 1][AVC]-NOGRP",
            "url": "https://a.111477.xyz/tvs/How%20I%20Met%20Your%20Mother/Season%204/How%20I%20Met%20Your%20Mother%20(2005)%20-%20S04E13%20-%20Three%20Days%20of%20Snow%20[Bluray-1080p%20Remux][DTS-HD%20MA%205.1][AVC]-NOGRP.mkv",
            "quality": "1080p | REMUX",
            "size": null,
            "type": "direct",
            "filename": "How I Met Your Mother (2005) - S04E13 - Three Days of Snow [Bluray-1080p Remux][DTS-HD MA 5.1][AVC]-NOGRP.mkv"
          },
          {
            "name": "DahmerMovies",
            "title": "DahmerMovies ][EAC3 5 1][h264]-FLUX",
            "url": "https://a.111477.xyz/tvs/How%20I%20Met%20Your%20Mother/Season%204/How%20I%20Met%20Your%20Mother%20(2005)%20-%20S04E13%20-%20Three%20Days%20of%20Snow%20[WEBDL-1080p][EAC3%205.1][h264]-FLUX.mkv",
            "quality": "1080p",
            "size": null,
            "type": "direct",
            "filename": "How I Met Your Mother (2005) - S04E13 - Three Days of Snow [WEBDL-1080p][EAC3 5.1][h264]-FLUX.mkv"
          }
        ],
        "count": 2
      }
    },
    {
      "key": "prov:moviesmod:tv:1100:s4e13",
      "storedAt": 1757793756772,
      "meta": {
        "storedAt": 1757793756,
        "urlCount": 1,
        "ttlSeconds": 0
      },
      "data": {
        "success": true,
        "provider": "moviesmod",
        "type": "tv",
        "tmdbId": "1100",
        "imdbId": "tt0460649",
        "season": 4,
        "episode": 13,
        "streams": [
          {
            "name": "MoviesMod",
            "title": "How I Met Your Mother S04E13 1080p 10Bit BluRay English Esubs Moviesmod Net\n543.34MB • 10-bit",
            "url": "https://video-downloads.googleusercontent.com/ADGPM2nu_iwM6jOd_a8fqeBTxQTkDMYkvl-VpfFQhU0tTyyx1BlXMFnY5-srI47FzPl-dRyztaLbf5gFpBU_AkStr4gHClOxLNw-F-Ep-hQEBJ1KPBLSCPe-3ZIyL_V21fyAQlEkt1yOq_LL2asJz58imvBgtFcbt7y0Xf71sqFJaIqK2n40HJYkqFr-xSWzYU1xwrksCgEZjAO96lX2tep5v-TBRdreNQwfqs0fOwJmdb1RlryfNdjUKq6tkYsIYSn3bmnGvthQ5rlhtRggHyZV9WTIBqVfUCaLArgx04A-vVeAliE6m5L7P1KOUBleQaaTmVXykHGpF7BOHe006Ay8O5fdFFGAOV8Bh9yMBejh2V4r5Z0qBA8vEvuuYFETGfXjbLVLCV980cPsRBPZJ2ocAKn0hjvXclmOJt7uow8jGaZL10G-ody7W677lGp4Jp0MNvWGf7TH_g2Fv26L8jonfkRgqm37NDA-JXHBIkQbmCOG_AYkMxoLpg3OseLfT66vtsMI_TLtT_38nahmXq1QZZDkuJzMqmnpbaqfiRDExpMsru9a__qsAEi3NTUUQWuRA5kMkQpVVv5697k-i7gEldsSFmmaOrJ0MgsHWKyB5Xuq3yJsSmEysJnb22RYqqapSx-SbBXcshKSNOC1xaakVXuyy5Tl4zAJaJW9Ol_Sm6JnGGgMayKCuUz-LC2rv89tzQk1WKaBRJzLp83t8_Y2ZI32gLaWYHLuXlS0JVxvjwx7nObLSRY3rMJgj4qRiePIAvPVcarDkAZ61W2QskxTUuRDZg9QywA8FAFSOQzHDSozH0ljmCdlqlWpd3oPQWqT2T9W0aZu1kVlwX1M6FWr7Jl2wO4T2cVuW6xER-rn35xJEvku0FBd7OSf4sXlx1YTsnlm4Tr-ayeRSUqLsI9M2Hr18AEX2rxxc5GoWr0vZRGpv-4WmD044h2FUePKzsVkqlGPqlO_E58V-HjlYgZ77aLjtpWaXrZ-jcKf8EZNpyyIIAjeJUsckJXn0D7Ij8DPKaEPtqBd5P_khnhR2nmyY7q6zcJ_pY5p2YQM_K2HaVMJbRu7c6Q",
            "quality": "1080p",
            "size": "543.34MB",
            "fileName": "How.I.Met.Your.Mother.S04E13.1080p.10Bit.BluRay.English.Esubs.Moviesmod.Net.mkv",
            "type": "direct"
          }
        ],
        "count": 1
      }
    },
    {
      "key": "prov:uhdmovies:tv:125910:s1e1",
      "storedAt": 1757793693139,
      "meta": {
        "storedAt": 1757793693,
        "urlCount": 1,
        "ttlSeconds": 0
      },
      "data": {
        "success": true,
        "provider": "uhdmovies",
        "type": "tv",
        "tmdbId": "125910",
        "imdbId": "tt14664414",
        "season": 1,
        "episode": 1,
        "streams": [
          {
            "name": "UHD Movies",
            "title": "Young Royals S01E01 2160p NF WEB-DL MULTi DDP5 1 HEVC~(Ionicboy)~SKiZOiD\n4.05GB",
            "url": "https://video-downloads.googleusercontent.com/ADGPM2k_4wKgAKONZUK5DirtF3SjFx1q_SJIIRl57XD3yNrJco8wldQWcUroNV6y_-mLfDqhznT6hWrXZlh5_jzp6VUjEjTcQzJEm8kV1HjO50Db4hNm-Xa-HAEKabdyeR4hlSvP6is66jId31kC2Sp93L8o9X2Qb183Kzq8SNy53uyUIE72PoaFbLFJQSWnfAkwlVoF36wzEVK0BnrowXr8IjcATLLkrZbf7eJ5VoVfD5-byRozXb7HFVTl6XUSdAdbCC-PXddLHAMKJMbZgJVoOVlDgJM2R2mc11XhBW65W3Ih6aKugeKnqeJ8xESL8F3X8X54rTNIhMYP7r1lDiNaBU3H6Cb4nu_OC4vDLy40j_MCxOWOddB3zdQznMwetxFUim0A_m-hcCVBsgIcB9_H31Z2cnlxZg-c-YhCGNJA9WCQ15X3qrIg4nksAeWOjv4hxbuJCbETIFflMC0xZ_9HOGbUDiUHYTntb39EMjmT3kwGyuK4xR_-FkYDqsGA05l-t4PtZuAA4JDjTHsKXf3FyUp9Zsuprhn_xMpir9RhnFf6EACWMzxRCanTJkH8wgmQkWoVVV7WZN3gGcxwOhbq3_V2u1f5THkjp4-sbDPtSRdqurSWKcPgJ7wDBAggZKzlgsQjxWESMjlSBRjsRA8XCOaL5qGF0HEK-6uwe_Su_-i6vsJruC-Mqumz7MD5c3eO3Zx0yrOn8v5s_nj2ZUe0SUgX6XZ31mDKp2OMGyT2rZX11at7YbwvrPsNiRbySvGbRG113M-006Cdbyu2gzjMeNJ2xUCH0Co548dIXCvL_vcBcXwVe2oHWzHBiJxCh2-objRWDv4W-p24mpkWJvFCy_UyJXv0jlwLdit0M7C_3P1Zk3IVzkb7LUdRK3-yNHER6Za-PyL4-myoJPIdxJ43JyEOdqGSqkfFPM3g5oXzY5ICpAOfzywYWz_GEccfwdIsv0yWy1H_rYIuLfpr1F9QMGCVuHlxjwi-lAEYUgkCvMsExPqHghAFTDd2UrsyL762acEjr1Eq1Rw_mdqFdzeuNrl4RoxB4wc4241aSPD7MoKs7yeJDlE",
            "quality": "4K",
            "size": "4.05GB",
            "fileName": "Young.Royals.S01E01.2160p.NF.WEB-DL.MULTi.DDP5.1.HEVC~(Ionicboy)~SKiZOiD.mkv",
            "type": "direct"
          }
        ],
        "count": 1
      }
    },
    {
      "key": "prov:dahmermovies:tv:1418:s1e4",
      "storedAt": 1757793757668,
      "meta": {
        "storedAt": 1757793757,
        "urlCount": 1,
        "ttlSeconds": 0
      },
      "data": {
        "success": true,
        "provider": "dahmermovies",
        "type": "tv",
        "tmdbId": "1418",
        "imdbId": "tt0898266",
        "season": 1,
        "episode": 4,
        "streams": [
          {
            "name": "DahmerMovies",
            "title": "DahmerMovies REMUX DTS-HD MA 5 1 Dual Hiro360",
            "url": "https://a.111477.xyz/tvs/The%20Big%20Bang%20Theory/Season%201/The.Big.Bang.Theory.S01E04.Bluray.1080p.REMUX.DTS-HD.MA.5.1.Dual.Hiro360.mkv",
            "quality": "1080p | REMUX",
            "size": null,
            "type": "direct",
            "filename": "The.Big.Bang.Theory.S01E04.Bluray.1080p.REMUX.DTS-HD.MA.5.1.Dual.Hiro360.mkv"
          }
        ],
        "count": 1
      }
    },
    {
      "key": "prov:moviesmod:tv:1418:s1e4",
      "storedAt": 1757793756556,
      "meta": {
        "storedAt": 1757793756,
        "urlCount": 4,
        "ttlSeconds": 0
      },
      "data": {
        "success": true,
        "provider": "moviesmod",
        "type": "tv",
        "tmdbId": "1418",
        "imdbId": "tt0898266",
        "season": 1,
        "episode": 4,
        "streams": [
          {
            "name": "MoviesMod",
            "title": "The Big Bang Theory S01E04 1080p 10Bit BluRay English Esubs Moviesmod In\n735.44MB • 10-bit",
            "url": "https://video-downloads.googleusercontent.com/ADGPM2niHEm1q1d0Q7yLDeL8oHndeuFwoiauNQ8zwL2cwVg3JxcOMkMUXnQlrFKBsqCcze0FsblP_xAMEvuyvPK29zNUHYHY3PDt-73RVaqEWfx7xcP9TUNy-pvav6iPt3qkiot1LWIwt9158oTkQz8PSOUR9uWHJkVwho7mVA0kAmX7BHde4goubXPA2MEyAUCOuaMxB3dYI7jPVni6LvYSCkzNf-glayZHRcVGKT45HO0powvqhEUk6-GINX2cR_7hRNtU3KwlzYICL4Nho2R-55wN3TjiVXsEVUrnCcEILDcsz7QlPrVGpnctXlP62IJNpw0egGNul_PH2rBTyv4iioexEAanvtUcgVsfvBN9lXr3dv4YsQAvRtphrCLhs4Y6yMuvkHBbBhFJs_fZk0gjcwKU2f_cu1eualkjxEUerW9n7TO-s-aFdMm3qcFGJvlCuuLtTkt6v3tEeEZRcGKkDmuxrvKJgNy_ZWGTBPlB8-aYaCNTM_Qxnr-oeTLdWVOXTbEWa7-Pua7Gra7CY4uBx_ZEwGHt1hq3yRbY3_mq4zHgPCZYkmwRTN-Wfip_hfCsOe5TBAmw79WbS0CclH38X16I40qT3A1JT91z6mNgxsLMUMYxLuWs1-rafpxQTaEuYlnmMQCqwVqO4bCeULviz2MXtIT11lGV_cQwlrduILDWj4giYJ8-aQM4ZcE8l6np0XexZ9WhSLEYpfjE61NXGCElPfWm-jz5kmhQZE7s6P_gcuv0fmb4ySBkTD0NK0k7wq8VBeAirM8PYqNj2X3GAj0BLMyBe4HA6ZQMzZSX8FCN9TYN3TH0RAAVVc_INLUhj2My40BnSxg8pihjXvjHstt039oA1CEnn-Z8J-lgYu2iTDYH6mVQdjhf0yw2jmjJ0EfGdYZeOI775gn6mKRhQIbjfhP83RLVQJJ7MpgnGA_HY_5gtQSF_CwiZCdQObk6od5bGn9RaYFxabNfR2SyYII5eMJapX6UecBahx6TjdRRHLo0CW6qrhie2-eb-4ZuZ8lHQ53MrLcoBQo7dVlsSxvB9IC4voKOc7hVcpGusssEPH6nBbA",
            "quality": "1080p",
            "size": "735.44MB",
            "fileName": "The.Big.Bang.Theory.S01E04.1080p.10Bit.BluRay.English.Esubs.Moviesmod.In.mkv",
            "type": "direct"
          },
          {
            "name": "MoviesMod",
            "title": "The Big Bang Theory S10E04 1080p 10Bit BluRay English Esubs Moviesmod In\n653.61MB • 10-bit",
            "url": "https://video-downloads.googleusercontent.com/ADGPM2k0p6ATDqnX-s6qsw-tHjisV5FG9dcPBHNIapp9uml0V8pCbYAqdRgb2TROMll9cjWyhXvyRx3-LxHUWvJ5AYzIydpqBSvfthrpeACxo1BpmU4R5Pz2c5irZF679cIBXWKmazD-HfzEEYAyP6we-c6fBH-ZdtCUz3NKrVDnBXATtHIhUAOwK77turMLDhVe6SBQZvJ5j8BUZ_NFGzxMOyI7EEejjqXbXTMEMVJIR2s9NS3bKjSmdRUoa0dabh4tcE8esmglGcScLCQTIjexm10fYyrJ2Pl4UOMASqsu6r2ms1QeOonDxpjIVIMQRb1dxKGt5hyr9Ae_WilimuGOR23E7vptvYqWmAhVmF8nJGBlCLPUyK7rl7IkYVeT2LKQrjNTyYWy7UciF1DDMlNLX4At-crD_oCuV-Opkt43i2UCEeFBVvJcFnf1p0g43srKZ9QwAuIvV6jJtRC9YWTFUWXw6C_PJtkwa2Zf8gndRTeGhT4Gx3NVeLaYnJyn58xMKiVjFpdzrOihnDtVhIKMVi-PCJNDXVH9tvRU8718DsI_LWkXjrLjZzsDFSxP2kPZXZ8LrkK8cg8CdOPogDyXd-lGpSULuGMb5Tix-Fc6qOgCzU2PkH8vBcyALC0spriv67zVI5CcZCpAyjImWbi1_LLtZPc0JZgJty39dxGE-HMXFC3ezcZXZTcecQPGS12AjY21h2SWfO3Fss8022gygF2C4ZgQ1a3nG6shlzfr3xjQZj-z09WG_o8qhsC1dCGBkgLdf9EBJ5HfLperMYgzHBEwxTz6SoP417XsM9McC6MLDKECPX_G4xsJ-dNfSlCVyWe4uPx028UjnfLcWhVPy-otESfiONgkpuzaeMyt-wwBSmcA7Kj93eQSOEDSY4pFOFdfR2EaktNmuiVoDp9iq3PI5eP9qKjoTGpU0Q-1La0D2HVEapiTB52k1T9hLTmUxrqqWv9W8qkPscL7xB_AqZI0spzYl-y_8ZO6yGH6BEnzOkqi0mUaRYFxU46BBp-7fVws1AdveLcPEHlhiq6x0uG1jWI46TXMTrN7oP06O1ZFL1HHlHc",
            "quality": "1080p",
            "size": "653.61MB",
            "fileName": "The.Big.Bang.Theory.S10E04.1080p.10Bit.BluRay.English.Esubs.Moviesmod.In.mkv",
            "type": "direct"
          },
          {
            "name": "MoviesMod",
            "title": "The Big Bang Theory S11E04 1080p 10Bit BluRay English Esubs Moviesmod In\n570.16MB • 10-bit",
            "url": "https://video-downloads.googleusercontent.com/ADGPM2nOwRk2D_j9HNC2A5vRQrdAp7uJRDJWOrm8LY66yGfmxEhRIdVFGe-4KK1JSEGiW2UYorz1MY9pvGTGJazhjtvkBbq4twOZEsX0FAJ5G6SSLh83g9BJwGmbNetLzJ7h-H8BNcxOUSi2Dc2G4axRx0bzH7sdnfQGgN_L6Hf5KyJD5YoWEVMqBN298nKPqzu5UWQTcZPPDzoWCTbE-LWn2CSOaMlIyQt3dUutnoqquWbRHZlF9qSxdx-6wHdBYkogCpIj6IwTTHoZr6V8CrK_vRC3AZLW_fgBnNb2QWUzyfKfwAq5-3XDaQnlsaxilES43WEmRjn0z4LJh_Q9qWQe7qjzeMYU8uuuqi_bNRs71SkSkRetBIFB4aMnau0vVmuEvcUt-kiQ-cmtnSLuYNPujQyrudP84Ce6CJjbT040Cosd8GBDZKpzf1340Bgvx-k1r9G5uRYpPLmWgDz0hq6Yw5MFzk3ibFK8sak2hth0XTU6QImt_ZRxPu4G9zR0HJ68P_jsC4NyyWBQfpAbXMtVbqQHYuiJBsbaPAeGBO2GTbMece3C2lNnbInZcYueRAL64Cqyb2lT4tchlc04bJxqZVv5UokMSGwsTZLrU2sXM2Br0m077Bql6M29Q27oToiPLC6weNLxjUnQNNerdi_XcXfnUfr5ywwstRb4tOCfx8qT7Z4_E0R3dqpY3FNuoDTpRQ8Kf58UzZOmPQ8c-s-PZsyjoWjRSOANDRvVVNI3QrWmIp0LcJhU0Ij7EO0E95JiSnKJ8igH68Qjt6xV9eZiTIMbWmnlbxcqqXz6uoExGgXFDzm7vFBGhZVWE948jPJ7o6hDhT8e6GRkA3ynlRyKHyUMa3bZv9AjkrAgQqzIoVIfTf2M7AlenAJ0QRfJlW7kTVNNxP840Ap_9NhBV1PWqM5PS4M9QOY2gkuEgvVd9FoAaiVIg3tY0gEh2i7ILuQjF91LcqD0XoFahnUUUEqzEE3WurnLOkMWZtfdHDYY5opW28fWmSr6gAx_janzV-zTRUmNSlNjbEEF8L90CEvAa8LFeniuaEA5Wdfd5XmAl4ESJv6px1g",
            "quality": "1080p",
            "size": "570.16MB",
            "fileName": "The.Big.Bang.Theory.S11E04.1080p.10Bit.BluRay.English.Esubs.Moviesmod.In.mkv",
            "type": "direct"
          },
          {
            "name": "MoviesMod",
            "title": "The Big Bang Theory S12E04 1080p 10Bit BluRay English Esubs Moviesmod In\n546.22MB • 10-bit",
            "url": "https://video-downloads.googleusercontent.com/ADGPM2lt85rD4T9-NnlkQnRGrvBTzUoLi30oO_Y0s6LdXNtJo2ePk5QahQblAThOI5k_hKAugSZD_cIMpkDZ7IBdIQexTROLRXgCAFmnMmOg1hbTO7hTYFBQTMx9mWggeizUVn_gFpsmxRyFShXjvICduOtEIXKmy_T_GMz0pJVGUZkSCqxAGytGWEJXcJcner1rNYAZNXu9_84yqpa_D52aXHbX0lMLQc6CWjQkVPl1CHXOLjn1jvhQsPt61XXbdGJWDgs19Qz4CK7SVuIeUWoVwiZsB7NzqwvG4C2hmAcaMEbYUxNkUuoqax4gxpvn7xg6E8rO8fXSFvghyZd4OmQMsw4mg5dhd6QZSlJUQXf72aOQ6J__Bx9VVBdwfPX6pizRrknWUvH0WplbAgGYZJKC79R_CNyHpH4_cm96RBa29PTmu0pYy3cxq04gkAopo5BkNbrElQELfsVFdANHMUkWIYQyK2oZfyO34DXmDgJqSx5s8brX25s0ZT6zDkAhjLdd-CUfJwsWVJF3lKuB_UI9VsYyuX4zjOszWkLxFbTDlVI1PeVOgP2MNTKJKQave3XjkZJyOj0b83uhAXDteGVT3XUNqIrAJkJjLlOyMwFfaI6UKT3IVg7syfkFHCCNyzJYfDIdDDks905AjcHyaS-LcLSvgLC-j2R_sQddAc1V0bHh1KD0J3_nrhN7T9vJQ3yiU2x4cIsl1hI1162OoirOx3jACY5GdBX_UPuxX62ktrfTRNFr3kjrK12zs1FjZ0aBhAq1oBCPhMDQyco1G33oL2RCnw8l9SdXgUdcOKJOQcINAnzvSfZNLtr4jR2HPeD8GzCsqt9sL_pmBVgCInPMocuzSjhY_RydYkXWfxNlXdpHmqCYEXJoj5DoKYCtvnCcKYxB6F0ReM7H3749l7fU6zsbA53rYndYINtBsXmfCoj7zcgZbP8Ztn9_8EBZqDnqOaFCK9vvbBxJxrVPZg-O0fTkXKQVObhQ0JCB4VaqzbsXa0z-OMIJEU8jdyTZrowLmTVmrcmfpo5CsdNRtHjjsI4nruqkTs6NYL25tv5UDo1tZV_Z9bU",
            "quality": "1080p",
            "size": "546.22MB",
            "fileName": "The.Big.Bang.Theory.S12E04.1080p.10Bit.BluRay.English.Esubs.Moviesmod.In.mkv",
            "type": "direct"
          }
        ],
        "count": 4
      }
    },
    {
      "key": "prov:4khdhub:tv:1447:s1e2",
      "storedAt": 1757793788276,
      "meta": {
        "storedAt": 1757793788,
        "urlCount": 1,
        "ttlSeconds": 0
      },
      "data": {
        "success": true,
        "provider": "4khdhub",
        "type": "tv",
        "tmdbId": "1447",
        "imdbId": "tt0491738",
        "season": 1,
        "episode": 2,
        "streams": [
          {
            "name": "4KHDHub - Pixeldrain - 1080p",
            "title": "Mob.Psycho.100.S01E02.1080p.AMZN.WEB-DL.Hindi.DDP2.0-Japanese.DDP2.0.H.264-4kHdHub.Com.mkv\n1.22 GB",
            "url": "https://pixeldrain.dev/api/file/K6kPUfzY?download",
            "quality": "1080p",
            "size": "1.22 GB",
            "fileName": "Mob.Psycho.100.S01E02.1080p.AMZN.WEB-DL.Hindi.DDP2.0-Japanese.DDP2.0.H.264-4kHdHub.Com.mkv",
            "type": "direct",
            "behaviorHints": {
              "bingeGroup": "4khdhub-streams"
            }
          }
        ],
        "count": 1
      }
    },
    {
      "key": "prov:4khdhub:tv:157741:s1e10",
      "storedAt": 1757793695149,
      "meta": {
        "storedAt": 1757793695,
        "urlCount": 1,
        "ttlSeconds": 0
      },
      "data": {
        "success": true,
        "provider": "4khdhub",
        "type": "tv",
        "tmdbId": "157741",
        "imdbId": "tt14186672",
        "season": 1,
        "episode": 10,
        "streams": [
          {
            "name": "4KHDHub - Pixeldrain - 2160p",
            "title": "Landman.S01E10.2160p.SKST.WEB-DL.H.265.DDP5.1-Tyrell.mkv\n8.66 GB",
            "url": "https://pixeldrain.net/api/file/p6kQaNug",
            "quality": "2160p",
            "size": "8.66 GB",
            "fileName": "Landman.S01E10.2160p.SKST.WEB-DL.H.265.DDP5.1-Tyrell.mkv",
            "type": "direct",
            "behaviorHints": {
              "bingeGroup": "4khdhub-streams"
            }
          }
        ],
        "count": 1
      }
    },
    {
      "key": "prov:dahmermovies:tv:157741:s1e10",
      "storedAt": 1757793698949,
      "meta": {
        "storedAt": 1757793698,
        "urlCount": 2,
        "ttlSeconds": 0
      },
      "data": {
        "success": true,
        "provider": "dahmermovies",
        "type": "tv",
        "tmdbId": "157741",
        "imdbId": "tt14186672",
        "season": 1,
        "episode": 10,
        "streams": [
          {
            "name": "DahmerMovies",
            "title": "DahmerMovies ][EAC3 5 1][h264]-NTb",
            "url": "https://a.111477.xyz/tvs/Landman/Season%201/Landman%20(2024)%20-%20S01E10%20-%20The%20Crumbs%20of%20Hope%20[WEBDL-1080p][EAC3%205.1][h264]-NTb.mkv",
            "quality": "1080p",
            "size": null,
            "type": "direct",
            "filename": "Landman (2024) - S01E10 - The Crumbs of Hope [WEBDL-1080p][EAC3 5.1][h264]-NTb.mkv"
          },
          {
            "name": "DahmerMovies",
            "title": "DahmerMovies ][AAC 5 1][x265]-KONTRAST",
            "url": "https://a.111477.xyz/tvs/Landman/Season%201/Landman%20(2024)%20-%20S01E10%20-%20The%20Crumbs%20of%20Hope%20[WEBRip-1080p][AAC%205.1][x265]-KONTRAST.mp4",
            "quality": "1080p",
            "size": null,
            "type": "direct",
            "filename": "Landman (2024) - S01E10 - The Crumbs of Hope [WEBRip-1080p][AAC 5.1][x265]-KONTRAST.mp4"
          }
        ],
        "count": 2
      }
    },
    {
      "key": "prov:moviesmod:tv:157741:s1e10",
      "storedAt": 1757793697559,
      "meta": {
        "storedAt": 1757793697,
        "urlCount": 3,
        "ttlSeconds": 0
      },
      "data": {
        "success": true,
        "provider": "moviesmod",
        "type": "tv",
        "tmdbId": "157741",
        "imdbId": "tt14186672",
        "season": 1,
        "episode": 10,
        "streams": [
          {
            "name": "MoviesMod",
            "title": "Landman S01E10 The Crumbs Of Hope 1080p x264 English Esubs MoviesMod cash\n1.52GB",
            "url": "https://video-downloads.googleusercontent.com/ADGPM2ko8Vww9c17MET4etzZQWhNym_26aG0F19NuPmUINr91iBQ-posGuXpDqTLVGmohRYUmf2Lh5nf3v-GseLKL4jGjIcoe6BN3gPe3_pTQsOtRWT4FVHLE4wvMr93lMJyvf-iB0Urz73mEnJ2Gv7AhM6If9FRHrG_bXpFROGPJipkPaMOIn2VIPSZnYJZKAmTb7Y-dItKbljcMMs0uWBNdm7V-pVk6AVN9juPcHAsLKrqorxqxy-NPx83ktjsgtGEPpi-rFGeBnj-xDyXynCmmk3AE4eyHKVm6DnvxnMsMxJSLjazb4yfh_U7ffpJMsOThBmVnHQxhGjDKskDbK6uneYTbFn5RrNK92h1voJ2xJUPyzPnhRPVU9p6PGSf3pLJc9y3x91lzWs8XUsrlONv5eJaBvluUA1sLOSlnI0kxWD9e87_Dt366lE-nmyx9HQbam7ZNs1tPoHHqVXsDhISU-Qcnd8stS7KIkJ_v7qtBQmtcfrWBQFAQ9Dg-ppiEain5jihn_piDPYpfzxqyMn9NZPnXQ7BycKWMIWjgL7FKi7jHOEWz7BcwKuA-9Y_4W4gdJbrHiffOH2I56IgzHDzhmaXB3dQ-WBV3LpxayoSf0zvFZasHALNF-CMqX949tcTjS8ehnfSKLxF4Gg2mK73WF-yHREY1ZY50xHiunT3Ziag-seVyJnfsK7vxOFP7dQhsublSgcbcC2rmuLVAAopjBBIYvaU8V7mqYDd0mmkGq00zmnSx2osYBfIq1k0AL4fbmU5Stz0HCUNEwI8URXJkmb1Wy5hXBC-XVh12niaUUP96s61rUuInSE1DA1Wt3bFjI0JxcTuUKWHRr7c6quajviWW5SRiDHRjITjrkx4PYnqWPpZngRruxINKoXch25xoySAVgz53RpZAU8IHZVcTJuOFxjoxmngT2YF3JZgy35ytfJ8J5aUuTzsJz3EvEPd7quQRh_LU4O7hs_b7Fyv4C0jNzuE5NRK1QTLRcBFrE19CLsmAAxJX57lQ0AHBLFU5cfh9fqbdJq58jaXsTVf8ykpMBqjUoIjvwfS13keMiCDZnrbXoI",
            "quality": "1080p",
            "size": "1.52GB",
            "fileName": "Landman.S01E10.The.Crumbs.Of.Hope.1080p.x264.English.Esubs.MoviesMod.cash.mkv",
            "type": "direct"
          },
          {
            "name": "MoviesMod",
            "title": "Landman S01E10 The Crumbs Of Hope 720p 10bit English Esubs MoviesMod cash\n423.46MB • 10-bit",
            "url": "https://video-downloads.googleusercontent.com/ADGPM2mlgixrowzz5Gf2m9Jhejw3QE7lLu3ELFJHVPtnLAeFA34pjq_fnXUAlZHJyz5EZ7aZtRmb1v2CIbnkrU3iNTowKL7DtuipuhFN857JomPW0JQ95KJ7-b724o8LjdxKA4B1pfwyOA8jo1hZGHnUquUoGTPwUjBup2r_AKz54wuoV7dpWW8LsUBTl2INHSCQbmE5vPMleKYmxifPNm0Co528_0z8Q9sZBvqeBh5Bef-xEJq7Tw26LxfKoWFwjm1E6yyVm2GMAHyEtLcnvEcWRb8ZrEnciEIdZCqBTxwtkVz1QUvjw5B4PK6m1sAERc7Af3cKS83iNuKTYcwpchl3mjgSQC2qKKO8mvvW6NMX7ivUfliYBOMqOGYyL7tuFs9Oa-3DYPIif8Na6gkGFzTv0Zv01LOgfDz0xKc214m3WvxVgiwvlCs250LrH5LMUzhnle0zLIHY0_4NpXFK4KzGnbnF7T8g5fWlz0QpbX8fHlLdB1FfzkHGKmsAAkSDBFf4U2HqjiismZCAyuPGyog8oWfd8oxKb-uVLRT00s4BDlVKFtTioz3PqaUghvod-wccs47Z_huGtH5LjGA_T8B5bbURGxRufLC_Dm6rP24QSrkW67DeGv8iIoiCQR5uKkouYLiqTT_5gIFLBUfWSQ0mIO_cX3GUsuPerJKfAWffkkMsFkOAUJtts-h_14S2rFxi6ohglv-XSCAMim4yEds3FGPF4_paFrU2DlhH8v8hcbnG2NRlpjRSTrQzQSRDzUhFLUpKNrE58DfUZlkRNC8GoKPwGVAanl38lJMMcMpIAzDal9l7K5i1Ad98VGPSvPRqcJ1MXCsjdISXyt7nhsnrLNPY2rEupIK128xDdC5SLX64JAz1sP6IY9c6B0UsLP9JTz12BjUiVdAV-CFc0oGUWbc3DI1yG8YTylLKFI4zmkm5hkRp-hlph2kKtSpUHahAXUMx0xfEfhQ5FxnJXenaHS-X_-Gt869h7r0XTxPSnPG41Tuv9ro6y-LxqV4KRGTCLS9MafWlXUfE03Zh61VearnboUaLpPSeCxct1I0arBMEYVJhGFo",
            "quality": "720p",
            "size": "423.46MB",
            "fileName": "Landman.S01E10.The.Crumbs.Of.Hope.720p.10bit.English.Esubs.MoviesMod.cash.mkv",
            "type": "direct"
          },
          {
            "name": "MoviesMod",
            "title": "Landman S01E10 The Crumbs Of Hope 720p x264 English Esubs MoviesMod cash\n652.29MB",
            "url": "https://video-downloads.googleusercontent.com/ADGPM2ksRPATJYROyOdHQbQIa6pYD_lOFvPrufFVLuxcEozH8XMepr02H6ZtJ5jynA6kN0ZqG7HGxz2YaXXDhvTpAFUuxFRbhUV3kI8Nwhu3H24V-6kG_k17xwC2xYUEEm84M-Z1TZYNkMuCaTJXpwh5lFl-DNzGUTzcnoEYnyKf24KWNOxA76xq7nV0-noQ3A4PKGtT6dmWEVXza5d6zVKjo_5u1kj2y9t4PJ1vpSk2Tt8LgQv2ebD4enQ7oZ_auVhqCmdzfwsxLpgAls22HvRVbf8xNGpIJoyGPAuelZf7vDLimMB8a3f7T5uyuOOUHDoaFXCglUhjrMwh5jMSXiE6Fz2nuQ2RDMtoNMJZM-hfgFDumQaJjWWIkkpcKqJHw_Lo3Q55HDLq2HAlLke43P1IXF8pySeDcaOpb2wnE-omYeFtXn7edIORgvXD7itTVW1Xz87bTEMByUgJsno-Pp8o9Hz197XvXDXo5WYABJzHaSMlVbT57TUsJZc__zJ0EwTULVMiubzQPsPfx2Y7l3_6vt7rk4XNzmFXyDB0OQ-zmikqdtj9NEgACXCuZM7O-zHJFNLHGmSHXE9zvv78mJUmC0vSBVa-Pd4SyhkfQa7BemRn1AzVI_Z6AjvO_2qE6VqodznUWnh0ZM9WElXvVQFIy9xoa5U8IWk6bK2hZG5DtyslvgT3imhVDHaA_KVZCuHJLxyBeuFPuzW9ZAWV2yDUGGjxTiwC_jH-waIXlDQNb4wjjVgseLAVfWMYP41RARd73sPbtk7DQQbdVwlXHu8K3lyW0b3NryuJhRYZfUeN5xBd8xTJQLZtfEWkyGw44KHh3zj6EcIq-KwBxFSYgVQ6Q_z-0KniBcZZP-pUyViZNpsgFSc0QQzB3LbgWmpxwZBveLgvgrZr3cKM89Tf_C5iMeFH-aeWgWEq-nU79k5B5Pf4EThzm1fisXJpQXIT6iJq8QA4h88n4-54x4d3tlJIsCKeZyZGX6oV30xk_lFYk9qeWQovAPiEL79jvqJ7IdI0vfC4fQc7fogiKzwR8EFvow5F7QMrlUTX-kMfkwaio3RtVbBff1w",
            "quality": "720p",
            "size": "652.29MB",
            "fileName": "Landman.S01E10.The.Crumbs.Of.Hope.720p.x264.English.Esubs.MoviesMod.cash.mkv",
            "type": "direct"
          }
        ],
        "count": 3
      }
    },
    {
      "key": "prov:dahmermovies:tv:1668:s10e6",
      "storedAt": 1757793768281,
      "meta": {
        "storedAt": 1757793768,
        "urlCount": 3,
        "ttlSeconds": 0
      },
      "data": {
        "success": true,
        "provider": "dahmermovies",
        "type": "tv",
        "tmdbId": "1668",
        "imdbId": "tt0108778",
        "season": 10,
        "episode": 6,
        "streams": [
          {
            "name": "DahmerMovies",
            "title": "DahmerMovies Remux][DV HDR10][10bit][HEVC][DTS-HD MA 5 1]-SiCFoI",
            "url": "https://a.111477.xyz/tvs/Friends/Season%2010/Friends%20(1994)%20-%20S10E06%20-%20The%20One%20with%20Rosss%20Grant%20[Bluray-2160p%20Remux][DV%20HDR10][10bit][HEVC][DTS-HD%20MA%205.1]-SiCFoI.mkv",
            "quality": "2160p | DV | HDR | REMUX",
            "size": null,
            "type": "direct",
            "filename": "Friends (1994) - S10E06 - The One with Rosss Grant [Bluray-2160p Remux][DV HDR10][10bit][HEVC][DTS-HD MA 5.1]-SiCFoI.mkv"
          },
          {
            "name": "DahmerMovies",
            "title": "DahmerMovies Bluray REMUX AVC DD 5 1-4K4U",
            "url": "https://a.111477.xyz/tvs/Friends/Season%2010/Friends.S10E06.The.One.With.Ross",
            "quality": "1080p | REMUX",
            "size": null,
            "type": "direct",
            "filename": "Friends.S10E06.The.One.With.Ross&#x27;s.Grant.1080p.Bluray.REMUX.AVC.DD.5.1-4K4U.mkv"
          },
          {
            "name": "DahmerMovies",
            "title": "DahmerMovies Friends (1994) - S10E06 - The One with Rosss Grant [DVD][MP3 2.0][XviD]-Saints.avi",
            "url": "https://a.111477.xyz/tvs/Friends/Season%2010/Friends%20(1994)%20-%20S10E06%20-%20The%20One%20with%20Rosss%20Grant%20[DVD][MP3%202.0][XviD]-Saints.avi",
            "quality": "Unknown | DV",
            "size": null,
            "type": "direct",
            "filename": "Friends (1994) - S10E06 - The One with Rosss Grant [DVD][MP3 2.0][XviD]-Saints.avi"
          }
        ],
        "count": 3
      }
    },
    {
      "key": "prov:uhdmovies:tv:1668:s10e6",
      "storedAt": 1757793767817,
      "meta": {
        "storedAt": 1757793767,
        "urlCount": 3,
        "ttlSeconds": 0
      },
      "data": {
        "success": true,
        "provider": "uhdmovies",
        "type": "tv",
        "tmdbId": "1668",
        "imdbId": "tt0108778",
        "season": 10,
        "episode": 6,
        "streams": [
          {
            "name": "UHD Movies",
            "title": "Friends S10E06 The One With Ross Grant 1080p BluRay REMUX AVC DD 5 1-EPSiLON\n2.75GB",
            "url": "https://video-downloads.googleusercontent.com/ADGPM2kvAB4xYciFCc49uJSRPXduucGsYj1sW_rxxaUdMlat2S8aRj6PRSHNzZjdXxLORXU9ZY5jbqvZLZ8ElKX6WG0ieKVLVhEHJkjmI-eJrqGQNQ8mUrvAsJN07Y1OWOF1ozyK3rKeMEwBzDPkriooBirqp0it3CS2vCsuJNNnRBrizUnNYqXBv4ZQ1eCNCwg-GlsSkm8OKsOyGFXd5zMVwa2PLTVyV59vJro0gi5CugOYUZTFE2v90w5j9onnvT1d9IvJvzj3YkgmG99I6FLWVQX5Hl7hYlF6N2K9F_tXK8JP2LItH1__JVgUOXBwmupHNLVtOmzY2Erd0BFHwalNbfVCxFYPW8mgGzJKJr29uPFxFeDc67T21JJBT7tidBEzrZjBY9K8UwoSQvysskAFPSjooFdw2B4wPep6UZH1u4AdrOUfZO0yqScWX3ObRJeXhP9KacRXmZYmGAYZAjR-eNy4vknPFCsYbZxriM_JahZlpivhikcwS1StAcNbUYTkchxI4LT3pkN5yb9H93JnzWBP6Jeq8ZWQUhEWUUmWv4qXWNTv9ZAYnYZetbwcHFSiwYTyqq-0R38c2_CySGCvmB2t-GoYvaDlfiyfD9jSqsM2bX9_HD4m1sun5cV8O0AS7QknlUN6Jk7L3yOAvLBT1LUlNbL31WxiZ0C0DGbNa0XeH_mFfYg1sXpAEko-LSS26Uivz8g7HO_oGYcxlWKvIcZF1sRC0zEXw12-yT7SBY-a6oAJJhs_C9OcPUy2oqf_PokOAUAc0m3_5MDMRMsoJQFKgBLT_3G9GOQAq6OtQv9NtqQsPqbC2i2eutfPMWbHXHEfNzNSw0RZZU2i4XVbL5pft3jCU4zuQK5P__ArOpLF8981wWppNFyCWUnEpI5SMyP81cHiFXWUifHNEZuMvoJgNopyOg6unKxmiw3BR3sE5BivCdeWEGa22ByReCYMC-LWOEbi3qccF7lRC5QjCI2Bnjz4GZQVcpfyUXkDyBKgFexn1RQIC2Ej4IA3Muqile2V1iYBPvovlYKRum4ePJes4pG-GxnM3l0hUKqVCWRqeI0sTW0",
            "quality": "1080p",
            "size": "2.75GB",
            "fileName": "Friends.S10E06.The.One.With.Ross.Grant.1080p.BluRay.REMUX.AVC.DD.5.1-EPSiLON.mkv",
            "type": "direct"
          },
          {
            "name": "UHD Movies",
            "title": "Friends S10E06 1080p NF WEB-DL DDP5 1 x264-TJUPT\n1.22GB",
            "url": "https://video-downloads.googleusercontent.com/ADGPM2k2ii3kRXMSAnfIQCPq_iApG-Z2WXCnvbUQkUhr1xzkVeO8um79lj6J_0oGwF1T3ovvlaI1xUrXhgiKYP5uQ84KEUawFpjRmYmiG5CrD1D6jFNsoi2fsCkeKp0Mzg_F9tytubDsTxTjWsp3NLo3NAwZE-JHpszFlN_75JFyiCGZo9fOMlP5zCPxz3XL5JESO3YLpWQHBzB1A80uZGrVMKgOwqZGaNe4JM4CKPEkFmx0urKRgK78O3nJiIUkhiCVoeVUbCMmaGIC5C4_G4mVpH2L2lvh9bucXUBr0hQyD4doO1VF39bXVVcYPjjhrfonBGEiQGWq5v-G7UtT3cU9HVgSGEYIHn9ur699_JYZvdxoWCG4tIXz8BTsBI-rYKvi3fLi5oP3DSOdNTH6RrLQPIpMWEG0SiQkQ87VH87uCB97H0kG-ibA_44Z_rP8TLfmUQ5J0UJUU6mbTu8zJxlHg8Uxzzsqkn0fbIW7N2Vhc7BoH9NqIXKSjb6ka0NX5Y4xXn8ZukrijTmxdXJ5qZSwnyQpo5GYZrHQliWcnaIFlBtN87UMJiEXZAY-AkLkU7sMGe72LwMmNLlanVBesy7mogyAAar3nGz2ROpCXSxz3PpSmhKRJuqWb7eE0ItaqoKJUps80RQzInVUC4B5pBHX5HcW4yOqyE6tHQuH6VPiM96GQoNOQOBzrfJtNaKxBX1lU4yqHqyFP3z33wmUNjd0k1gyD4WK5Cn5-PStJJIw3rlIhP31_IdHjPH8sOz3Fa4bLaowbPNQ8i8VGooNpPEgB9vlPP4BxRdsqiH949ZRWudpwaIfBK9syxns4CM_7b3Bee_lPVXCB3qe1v0yMS6Gwh2X2oz_Y9Vj6TOEYUXCY5esItcbfMOFa16ywG2puvA7u8d4t4vtUrkPfxBeEDVqcXgCXM1fSaWjQXJ-jcxDbWqIuO7kzn5ozbrKUnX8kOB1RT-4VUtGVIBoTivfOSDsAACRWv2WVAb9sm9cTuovIqeSLKCoEmA1oNv-INWetTXZUCPwwN-VeUS_Zezndxei5zpK_GLFQJr2WATDWydOdZxXh_tiVuw",
            "quality": "1080p",
            "size": "1.22GB",
            "fileName": "Friends.S10E06.1080p.NF.WEB-DL.DDP5.1.x264-TJUPT.mkv",
            "type": "direct"
          },
          {
            "name": "UHD Movies",
            "title": "Friends S10E06 The One With Ross&#039;s Grant  (1080p x265 10bit Joy)\n260.61MB",
            "url": "https://video-downloads.googleusercontent.com/ADGPM2lokADCezy2BtEDVD4OeEmBjPtcuQ5F_3DYIYznTUL89s5HSRp6jPBdghW57fJl40vDj1jgijZH545jwK17eWDaEC8Zk7ETPp80ErNYYZgKu1mQJIbr5PrC5XqQHHCcJl0wwKD3rhnPTWusQgzkHWXbQQD8plNqF8UvnT197TobtfprP9bAtGAFChDqFRNYaTb3VXqZCFNJ39Er63jfnlxw8lMWCnKflJcSfiZjKLEYS7901J0GdizMIwZNzY3SgiDmyXh1Ah_S_OrEPi_Os3kHNitkYQDCxh7v7RowV_x99FemmxVa2OfELttG2obK09s5JDBjApUPahL7wi8ba6gkvM6Zd1qSlAgwMugv7Lq4M6DeM2Dg5fp09QRdJT6vqpq1CFSX4ma-kxrmM4GVCk98mL9B_YOqe5gMgqzbTv0QOggISxL4HPs2ziAJr8K-VqgM64neejLTH-pvA_kd_ENKOJp47GcS6kAHRRLW910nqDP0GayMqQmwrYlHCE4vOhhQvwuYrU4m3TT5q8ISvJkclw09flSrygZJv-rQaAw6e_fYMm-0kyUGgRqJqmCcAQt-Hg7jgZxPuUp6Gl64CgGmF9r2ECK5vFlncmdXEro4nZjqSQ9-oigkPouH3T2kvSDQG7HC0AAg0Tmn3HAfjakh-GR8xlVmfqXiDECLupC-E1CnrwPyOCFOWRLf0DauwTMVQrxHYSySz-YvdF5UIVTtyXucbCYOkPqVRPfCNYhU5pOx7OveqLmduO1e4T1WrzP28kb-AYX5Mr7xPmUwR1NSNWkVVhM3hYtZMK5xaxzRtsqjAPs65AuD_QfQZRl8kDGe-1_xlEwTI_D3a7voPyoPvlIDymKtkKEOS6OKYUL8UqeBtsC5oEhwdAvotCDieGmnqxO9US8PbTNjdTTN2C7SwRxIWtf3PfhTDNQU6DpjuOOhM6HEmGKmuBczVG-Yj969cbP-aMI3GmtgGztTrl6S1OTR61H1uZYsXUqjorosSwb0jYNJqtT0g5dYs1Agwir0zE0YNhR7rGVcBjyKgpwIjKbaFi7R33Zo7cZp_P6ZWJru2Q8",
            "quality": "1080p",
            "size": "260.61MB",
            "fileName": "Friends S10E06 The One With Ross&#039;s Grant  (1080p x265 10bit Joy).mkv",
            "type": "direct"
          }
        ],
        "count": 3
      }
    },
    {
      "key": "prov:4khdhub:tv:18165:s1e7",
      "storedAt": 1757793788985,
      "meta": {
        "storedAt": 1757793788,
        "urlCount": 6,
        "ttlSeconds": 0
      },
      "data": {
        "success": true,
        "provider": "4khdhub",
        "type": "tv",
        "tmdbId": "18165",
        "imdbId": "tt1405406",
        "season": 1,
        "episode": 7,
        "streams": [
          {
            "name": "4KHDHub - Pixeldrain - 1080p",
            "title": "The.Vampire.Diaries.S01E07.1080p.DD5.1.VC-1.REMUX-FraMeSToR.mkv\n5.48 GB",
            "url": "https://pixeldrain.dev/api/file/wP2naWJv?download",
            "quality": "1080p",
            "size": "5.48 GB",
            "fileName": "The.Vampire.Diaries.S01E07.1080p.DD5.1.VC-1.REMUX-FraMeSToR.mkv",
            "type": "direct",
            "behaviorHints": {
              "bingeGroup": "4khdhub-streams"
            }
          },
          {
            "name": "4KHDHub - FSL Server - 1080p",
            "title": "The.Vampire.Diaries.S01E07.1080p.DD5.1.VC-1.REMUX-FraMeSToR.mkv\n5.48 GB",
            "url": "https://pub-52f57cc1b81f4ecdac02802c1566c33d.r2.dev/The.Vampire.Diaries.S01E07.1080p.DD5.1.VC-1.REMUX-FraMeSToR.mkv?token=1757793788",
            "quality": "1080p",
            "size": "5.48 GB",
            "fileName": "The.Vampire.Diaries.S01E07.1080p.DD5.1.VC-1.REMUX-FraMeSToR.mkv",
            "type": "direct",
            "behaviorHints": {
              "bingeGroup": "4khdhub-streams"
            }
          },
          {
            "name": "4KHDHub - Pixeldrain - 1080p",
            "title": "The.Vampire.Diaries.S01E07.Haunted.1080p.HMAX.WEB-DL.DD5.1.H.264-playWEB.mkv\n2.4 GB",
            "url": "https://pixeldrain.dev/api/file/yfC9hh1j?download",
            "quality": "1080p",
            "size": "2.4 GB",
            "fileName": "The.Vampire.Diaries.S01E07.Haunted.1080p.HMAX.WEB-DL.DD5.1.H.264-playWEB.mkv",
            "type": "direct",
            "behaviorHints": {
              "bingeGroup": "4khdhub-streams"
            }
          },
          {
            "name": "4KHDHub - FSL Server - 1080p",
            "title": "The.Vampire.Diaries.S01E07.Haunted.1080p.HMAX.WEB-DL.DD5.1.H.264-playWEB.mkv\n2.4 GB",
            "url": "https://pub-52f57cc1b81f4ecdac02802c1566c33d.r2.dev/The.Vampire.Diaries.S01E07.Haunted.1080p.HMAX.WEB-DL.DD5.1.H.264-playWEB.mkv?token=1757793788",
            "quality": "1080p",
            "size": "2.4 GB",
            "fileName": "The.Vampire.Diaries.S01E07.Haunted.1080p.HMAX.WEB-DL.DD5.1.H.264-playWEB.mkv",
            "type": "direct",
            "behaviorHints": {
              "bingeGroup": "4khdhub-streams"
            }
          },
          {
            "name": "4KHDHub - Pixeldrain - 1080p",
            "title": "The Vampire Diaries 2009 S01E07 Haunted 1080p BluRay x265 10-Bit SDR DDP 5.1 English - DarQ.mkv\n1.52 GB",
            "url": "https://pixeldrain.dev/api/file/EicFfyzV?download",
            "quality": "1080p",
            "size": "1.52 GB",
            "fileName": "The Vampire Diaries 2009 S01E07 Haunted 1080p BluRay x265 10-Bit SDR DDP 5.1 English - DarQ.mkv",
            "type": "direct",
            "behaviorHints": {
              "bingeGroup": "4khdhub-streams"
            }
          },
          {
            "name": "4KHDHub - FSL Server - 1080p",
            "title": "The Vampire Diaries 2009 S01E07 Haunted 1080p BluRay x265 10-Bit SDR DDP 5.1 English - DarQ.mkv\n1.52 GB",
            "url": "https://pub-52f57cc1b81f4ecdac02802c1566c33d.r2.dev/The%20Vampire%20Diaries%202009%20S01E07%20Haunted%201080p%20BluRay%20x265%2010-Bit%20SDR%20DDP%205.1%20English%20-%20DarQ.mkv?token=1757793788",
            "quality": "1080p",
            "size": "1.52 GB",
            "fileName": "The Vampire Diaries 2009 S01E07 Haunted 1080p BluRay x265 10-Bit SDR DDP 5.1 English - DarQ.mkv",
            "type": "direct",
            "behaviorHints": {
              "bingeGroup": "4khdhub-streams"
            }
          }
        ],
        "count": 6
      }
    },
    {
      "key": "prov:dahmermovies:tv:219543:s1e6",
      "storedAt": 1757793760652,
      "meta": {
        "storedAt": 1757793760,
        "urlCount": 1,
        "ttlSeconds": 0
      },
      "data": {
        "success": true,
        "provider": "dahmermovies",
        "type": "tv",
        "tmdbId": "219543",
        "imdbId": "tt26545355",
        "season": 1,
        "episode": 6,
        "streams": [
          {
            "name": "DahmerMovies",
            "title": "DahmerMovies ][EAC3 5 1][x264]-FLUX",
            "url": "https://a.111477.xyz/tvs/Creature%20Commandos/Season%201/Creature%20Commandos%20(2024)%20-%20S01E06%20-%20Priyatel%20Skelet%20[WEBDL-1080p][EAC3%205.1][x264]-FLUX.mkv",
            "quality": "1080p",
            "size": null,
            "type": "direct",
            "filename": "Creature Commandos (2024) - S01E06 - Priyatel Skelet [WEBDL-1080p][EAC3 5.1][x264]-FLUX.mkv"
          }
        ],
        "count": 1
      }
    },
    {
      "key": "prov:moviesmod:tv:219543:s1e6",
      "storedAt": 1757793758092,
      "meta": {
        "storedAt": 1757793758,
        "urlCount": 1,
        "ttlSeconds": 0
      },
      "data": {
        "success": true,
        "provider": "moviesmod",
        "type": "tv",
        "tmdbId": "219543",
        "imdbId": "tt26545355",
        "season": 1,
        "episode": 6,
        "streams": [
          {
            "name": "MoviesMod",
            "title": "Creature Commandos S01E06 Priyatel Skelet 1080p x264 English Esubs MoviesMod cash\n1014.62MB",
            "url": "https://video-downloads.googleusercontent.com/ADGPM2kSBf4tkCETe4nDT39lShwIrLR5OR_gnY30jtlkYXYiMuUM3wIkeDKdiu1dKXkSDn04HixSE06n1UT9WoXIlEu_nhHi61UD-_v3Fi_wcdNMuWPHhoo8nrUr7R2IZDFUVWS7h6zBihF_q2cBoAX6w-xpAEDLWCUoY6AbP3aQMn0oJfj72IqCM3pMExP1Un4WjNq3WfDyyN0EBKY2EnfhIqMLPRMe3vGyfPhePZL7pzM-lHhJdnM8thK8gbtpThedJfBir5O3204HvK7giqN1YgS_spv9-e2E8lU0cYKPU24oO-JHs9BsWQ9_wwqYAFOwkhwHBTQETVkeCkR6wDpuV5saSuFsT4SfqS6jbAbLTMxZqaHv9_iE5K7yRciBNI3L32jB6IGS4RIuMDi7qwFfhdysJQxWMLu3WFF0xp0zK8s2hzZSlJQXY4NOxq2aIHEcbrEXnA6upQqbKFfFJITtOMpRO8KlAEBFYKeYpfBBXmWt7ekuNIa9REPSgbxs0WjHslEHGi7KMmSi9I0E0H-v5iMPGAEQQMg9hozn8b2FV4IHaIVawKOlCY47Q8FUIlJ6JhU0c_UaySRPX1CP0aYvCdZ_9zl1tOD5RGqJ3Q5E__CGelAZmbt9QG8tqCMyUC-vca_Ykfj0K4RyNVxdRDzdJG863j-_H72x-OraAoOVWIP2kvVHWQ4OTfyyhJCb8Ns-YMsK3qjLGBf7U5ipemtHdLHADsMCb0LR7gn1NCAvSs3mVI1_kAQY6HBBRfewKk_7Mj1GXrMHrEAZL3X2xMj_82wrSQGEyKo2DixYFOvCZ_JTIsg27Gp6qx0f9PbdawRV85zCm2ijXNFDter1D5S9w7VJAQAGisiraddSB12YEhHGKPOsyJa2neB93tL39gylVGjFkCEEzxk4Vpy6mmX6wIyHgRQTgL223dQn0nbYqO1S7XYAygROrw2up_SsyrjlcbdPEk_wIWgX65UiX2FL0HsREzCoe-3sTfADVSiQvDIbFUpRLWFkuPurTUUN3HXzUXO6kC4GaYHZ0pJKr1-E_QFcAdJkEX1l7SXg7q1I5h6OjFPvUSc",
            "quality": "1080p",
            "size": "1014.62MB",
            "fileName": "Creature.Commandos.S01E06.Priyatel.Skelet.1080p.x264.English.Esubs.MoviesMod.cash.mkv",
            "type": "direct"
          }
        ],
        "count": 1
      }
    },
    {
      "key": "prov:dahmermovies:tv:234927:s1e12",
      "storedAt": 1757793773780,
      "meta": {
        "storedAt": 1757793773,
        "urlCount": 2,
        "ttlSeconds": 0
      },
      "data": {
        "success": true,
        "provider": "dahmermovies",
        "type": "tv",
        "tmdbId": "234927",
        "imdbId": "tt29218693",
        "season": 1,
        "episode": 12,
        "streams": [
          {
            "name": "DahmerMovies",
            "title": "DahmerMovies ][AAC 2 0][x264]-NTb",
            "url": "https://a.111477.xyz/tvs/Baddies%20East/Season%201/Baddies%20East%20(2023)%20-%20S01E12%20-%20National%20Forgiveness%20Day%20[WEBDL-1080p][AAC%202.0][x264]-NTb.mkv",
            "quality": "1080p",
            "size": null,
            "type": "direct",
            "filename": "Baddies East (2023) - S01E12 - National Forgiveness Day [WEBDL-1080p][AAC 2.0][x264]-NTb.mkv"
          },
          {
            "name": "DahmerMovies",
            "title": "DahmerMovies Baddies East - S01E12 - National Forgiveness Day WEBDL-1080p.mkv",
            "url": "https://a.111477.xyz/tvs/Baddies%20East/Season%201/Baddies%20East%20-%20S01E12%20-%20National%20Forgiveness%20Day%20WEBDL-1080p.mkv",
            "quality": "1080p",
            "size": null,
            "type": "direct",
            "filename": "Baddies East - S01E12 - National Forgiveness Day WEBDL-1080p.mkv"
          }
        ],
        "count": 2
      }
    },
    {
      "key": "prov:4khdhub:tv:241315:s1e1",
      "storedAt": 1757793684924,
      "meta": {
        "storedAt": 1757793684,
        "urlCount": 2,
        "ttlSeconds": 0
      },
      "data": {
        "success": true,
        "provider": "4khdhub",
        "type": "tv",
        "tmdbId": "241315",
        "imdbId": "tt35507572",
        "season": 1,
        "episode": 1,
        "streams": [
          {
            "name": "4KHDHub - Pixeldrain - 1080p",
            "title": "Mouse.S01E01.EPISODE.1.1080p.AMZN.WEB-DL.Korean.DDP2.0.H.264-4kHdHub.Com.mkv\n5.56 GB",
            "url": "https://pixeldrain.dev/api/file/4JwUEpYj?download",
            "quality": "1080p",
            "size": "5.56 GB",
            "fileName": "Mouse.S01E01.EPISODE.1.1080p.AMZN.WEB-DL.Korean.DDP2.0.H.264-4kHdHub.Com.mkv",
            "type": "direct",
            "behaviorHints": {
              "bingeGroup": "4khdhub-streams"
            }
          },
          {
            "name": "4KHDHub - FSL Server - 1080p",
            "title": "Mouse.S01E01.EPISODE.1.1080p.AMZN.WEB-DL.Korean.DDP2.0.H.264-4kHdHub.Com.mkv\n5.56 GB",
            "url": "https://pub-52f57cc1b81f4ecdac02802c1566c33d.r2.dev/Mouse.S01E01.EPISODE.1.1080p.AMZN.WEB-DL.Korean.DDP2.0.H.264-4kHdHub.Com.mkv?token=1757793684",
            "quality": "1080p",
            "size": "5.56 GB",
            "fileName": "Mouse.S01E01.EPISODE.1.1080p.AMZN.WEB-DL.Korean.DDP2.0.H.264-4kHdHub.Com.mkv",
            "type": "direct",
            "behaviorHints": {
              "bingeGroup": "4khdhub-streams"
            }
          }
        ],
        "count": 2
      }
    },
    {
      "key": "prov:uhdmovies:tv:255529:s1e1",
      "storedAt": 1757793725882,
      "meta": {
        "storedAt": 1757793725,
        "urlCount": 2,
        "ttlSeconds": 0
      },
      "data": {
        "success": true,
        "provider": "uhdmovies",
        "type": "tv",
        "tmdbId": "255529",
        "imdbId": "tt4151288",
        "season": 1,
        "episode": 1,
        "streams": [
          {
            "name": "UHD Movies",
            "title": "The Originals S01E01 Always and Forever 1080p BluRay Remux AVC DTS-HD MA 5 1-EPSiLON\n5.67GB",
            "url": "https://video-downloads.googleusercontent.com/ADGPM2lfYW9OHyL82nqe2MjimIuJ4pkeXXNdeLxPmi4D40QryY83yqV8pkEB3OkqJWl84ISGn-4694YY1juIC83fyYEREk4OTku2_h5goRNZq13zzAWD3zM2JOPjElhg9QWZvBlDJ7xQrhyPNwZ_DHfhsEVn-cAe5243VOD6daxQtyH8a33JeaqtsWdeDVA3fUE6pk2DPImqiOrVx5LtjPzUE-GuFU_HaCOLN9CbYejduaVT_ux4xKFXHgaEzF-1ilmefVbaZgWSn9J6xgDiBWO9DX8JkMtHiMfs1de7vp8Z7Qd-souN7PabM0zlqxaNaNJwpW_EXO-9dWQUP_rbTtYFXj7yNqPpvYyjU7ClN1BjDaIUoaVeDZK0Y--w8_J1lejJUcNZY5zlgF3NJkfRDb1uUgJ5eTSrjPKh1gJUE7wDujwDFkAwMrISmlaUoK4WNKTZHeOBn-3v1HHDou0WrBhfJCbO0yswIgrYebNClDMNppXYVLveJWI1OJy0_-7o_WxZkao36Iz8GEA7A_QTQ8jWkIx7x6OdIifJh-LkZEKH7owjY1MOe3tvquCxMmeWa5e8QQPgCR9R1MZocojU4WD2E1HeunM6BaF8I3GFZXIKzWLaCZ0nX3emk2Urzr2qgyW1lWpuJPhnMR1RIO_48tEUuKgZVpHNh9wWkPpPk0Kwv4DbVSzg3TeJPMELwvBWtTDMBXi9-UGKzEeA1D7Kz8b-KxnB_3AKWlQmazM7X_SNqil0aW6tIkGuA0dSdcWDo2XVbMCznUf-Oso74CDKJhU12UOnw75UeM_auFR6DqhhiLCxQ8qGZn6rRStkM110r5F2EmEoVoi-wdpriYVJn9m_Ppx1L7BpQu4pE04siKga85vcA4_ZheJcoLn3XAhtd79I-MyVqU5rMSwq9c9amJxA4EzxvDSQQWnKr6TcqaO6X0MiDhnPp11z9ugVOBfFL5pm06r8I-6Duw0TpoOTS_x3VK4Xjrhmk-QgphaKbUfe8n-4pZRuJlcfsDM4IS1yWqTi3mi5nUbqdlyTpoiBPzb36X3ENc2AqSaghxN1wmjhVSxNgp8CfnQ",
            "quality": "1080p | BluRay",
            "size": "5.67GB",
            "fileName": "The.Originals.S01E01.Always.and.Forever.1080p.BluRay.Remux.AVC.DTS-HD.MA.5.1-EPSiLON.mkv",
            "type": "direct"
          },
          {
            "name": "UHD Movies",
            "title": "The Originals S01E01 1080p BluRay 10bit H265-d3g\n1.45GB",
            "url": "https://video-downloads.googleusercontent.com/ADGPM2kRFLobF7LWgBrLJ5MuF1LURsTKo4S07Mq0Z0nRBBi4bW-q0xmhiFD__BNJNZC983IM62ZNxsPRD3VKLh6FROo2GtB5WJeJLVGItzosxsKBVuKZPeTdly-1NK1WEqWNq3S88nbUn0kEn6hrJIIhfA_n8rMhf-AZPEwH17eVgB7dy4G1SiXSuK0c5q0WItljGveDbV0Wk8n23CT96YB4-shCVJY5Nbb_IjrmRUruVbtxcWVabafosp-MJekQ-BkhSEtFmIphhHkY0SMB3b8CyJKAlLKHU3qBYaGqpn0DttOtWCmWtzB5Nrlr4UOUssVGj62UPb61pqI6uS4L9ba072QA3meCQQXgvWvjVDAZcN9x5WEEl2XF4hP6k5YPhdAaXaLTP-HeKhLD5jDpfn5bZEE-7JeUZf6IFAM_xUNMgBqeOOw5pqq0HLMuBb0EVdm0nq6ZhvBLdRpfJ1vSspDp5EZVIDo-p-rMZpYNZUomdaECyljE1nJtDfKIgZBlFOrzRg7JCV_MXbi8uR2Lvg0Wul5hdAl7W9UAB1vaSFEmaQ-dmiHwQ2RrCI-RAd97ZyaJYlPo1wfF9bpBk7NeSm2cyi0KPT3nVIh6mXpfY7vNTqsfCVGwRmbyqSzQ7tODUoccidkEJbChfxV-Mr45iRmAhW3PEiD6qrDb429XqKv3HDIDUWCZWmxtqe5D9X8bVVqzzlxPUccARBkDPP3ns8Ij0w3FTkamMlYiAsvIytS4ACZLqe60wAAFxP6tcqvMOewrSWUAXSms9QeCGsJQuycXRVDl8Np7gjq3ZY53190HY62ewNL1YjXAlHBUj1RR9Yj-yj1X6IpAbWkFny-b8FFcZiCzgI5INu-zc1NIb8c2lKJF1keh1ON4JU9l4SkkMdSj84_zhuslJ3o7w9sZu7NTgSD_9ywGuu_3FtXjoyY0PIqgANKf9p6rZF-LXmTdD15oywPWhv2bUlWTEhuY62YWalO7HdT3H14-QMwe5lP-xVE3sTWT7uUoU9AYP4GtuklwmzdB1U9j4ENHDtqe8GsilH_x775Z_0lZHJpEahfIuo4r9jlIoT4",
            "quality": "1080p | BluRay",
            "size": "1.45GB",
            "fileName": "The.Originals.S01E01.1080p.BluRay.10bit.H265-d3g.mkv",
            "type": "direct"
          }
        ],
        "count": 2
      }
    },
    {
      "key": "prov:dahmermovies:tv:35279:s2e1",
      "storedAt": 1757793769061,
      "meta": {
        "storedAt": 1757793769,
        "urlCount": 1,
        "ttlSeconds": 0
      },
      "data": {
        "success": true,
        "provider": "dahmermovies",
        "type": "tv",
        "tmdbId": "35279",
        "imdbId": "tt1830491",
        "season": 2,
        "episode": 1,
        "streams": [
          {
            "name": "DahmerMovies",
            "title": "DahmerMovies ][EAC3 5 1][h264]-SOMERSAULT",
            "url": "https://a.111477.xyz/tvs/Austin%20&%20Ally/Season%202/Austin%20&%20Ally%20(2011)%20-%20S02E01%20-%20Costumes%20and%20Courage%20[WEBDL-1080p][EAC3%205.1][h264]-SOMERSAULT.mkv",
            "quality": "1080p",
            "size": null,
            "type": "direct",
            "filename": "Austin &amp; Ally (2011) - S02E01 - Costumes and Courage [WEBDL-1080p][EAC3 5.1][h264]-SOMERSAULT.mkv"
          }
        ],
        "count": 1
      }
    },
    {
      "key": "prov:dahmermovies:tv:38472:s1e1",
      "storedAt": 1757793738697,
      "meta": {
        "storedAt": 1757793738,
        "urlCount": 1,
        "ttlSeconds": 0
      },
      "data": {
        "success": true,
        "provider": "dahmermovies",
        "type": "tv",
        "tmdbId": "38472",
        "imdbId": "tt2357547",
        "season": 1,
        "episode": 1,
        "streams": [
          {
            "name": "DahmerMovies",
            "title": "DahmerMovies ][DTS 5 1][x264]-ROVERS",
            "url": "https://a.111477.xyz/tvs/Marvel",
            "quality": "1080p",
            "size": null,
            "type": "direct",
            "filename": "Marvel&#x27;s Jessica Jones (2015) - S01E01 - AKA Ladies Night [Bluray-1080p][DTS 5.1][x264]-ROVERS.mkv"
          }
        ],
        "count": 1
      }
    },
    {
      "key": "prov:dahmermovies:tv:4586:s3e21",
      "storedAt": 1757793685669,
      "meta": {
        "storedAt": 1757793685,
        "urlCount": 3,
        "ttlSeconds": 0
      },
      "data": {
        "success": true,
        "provider": "dahmermovies",
        "type": "tv",
        "tmdbId": "4586",
        "imdbId": "tt0238784",
        "season": 3,
        "episode": 21,
        "streams": [
          {
            "name": "DahmerMovies",
            "title": "DahmerMovies ][EAC3 2 0][x264]-CONVOY",
            "url": "https://a.111477.xyz/tvs/Gilmore%20Girls/Season%203/Gilmore%20Girls%20(2000)%20-%20S03E21%20-%20Here%20Comes%20the%20Son%20[WEBDL-1080p][EAC3%202.0][x264]-CONVOY.mkv",
            "quality": "1080p",
            "size": null,
            "type": "direct",
            "filename": "Gilmore Girls (2000) - S03E21 - Here Comes the Son [WEBDL-1080p][EAC3 2.0][x264]-CONVOY.mkv"
          },
          {
            "name": "DahmerMovies",
            "title": "DahmerMovies ][EAC3 2 0][x264]-TrollHD",
            "url": "https://a.111477.xyz/tvs/Gilmore%20Girls/Season%203/Gilmore%20Girls%20(2000)%20-%20S03E21%20-%20Here%20Comes%20the%20Son%20[WEBDL-1080p][EAC3%202.0][x264]-TrollHD.mkv",
            "quality": "1080p",
            "size": null,
            "type": "direct",
            "filename": "Gilmore Girls (2000) - S03E21 - Here Comes the Son [WEBDL-1080p][EAC3 2.0][x264]-TrollHD.mkv"
          },
          {
            "name": "DahmerMovies",
            "title": "DahmerMovies WEB-DL DD+ 2 0 x264-TrollHD",
            "url": "https://a.111477.xyz/tvs/Gilmore%20Girls/Season%203/Gilmore%20Girls%20S03E21%201080p%20WEB-DL%20DD+%202.0%20x264-TrollHD.mkv",
            "quality": "1080p",
            "size": null,
            "type": "direct",
            "filename": "Gilmore Girls S03E21 1080p WEB-DL DD+ 2.0 x264-TrollHD.mkv"
          }
        ],
        "count": 3
      }
    },
    {
      "key": "prov:4khdhub:tv:69541:s1e3",
      "storedAt": 1757793789904,
      "meta": {
        "storedAt": 1757793789,
        "urlCount": 3,
        "ttlSeconds": 0
      },
      "data": {
        "success": true,
        "provider": "4khdhub",
        "type": "tv",
        "tmdbId": "69541",
        "imdbId": "tt5761478",
        "season": 1,
        "episode": 3,
        "streams": [
          {
            "name": "4KHDHub - Pixeldrain - 2160p",
            "title": "Harlem.S01E03.Rainbow.Sprinkles.2160p.AMZN.WEB-DL.Hindi.DDP5.1-English.DDP5.1.H.265-4kHdHub.Com.mkv\n3.87 GB",
            "url": "https://pixeldrain.dev/api/file/94o5BTze?download",
            "quality": "2160p",
            "size": "3.87 GB",
            "fileName": "Harlem.S01E03.Rainbow.Sprinkles.2160p.AMZN.WEB-DL.Hindi.DDP5.1-English.DDP5.1.H.265-4kHdHub.Com.mkv",
            "type": "direct",
            "behaviorHints": {
              "bingeGroup": "4khdhub-streams"
            }
          },
          {
            "name": "4KHDHub - Pixeldrain - 2160p",
            "title": "Harlem.S01E03.Rainbow.Sprinkles.2160p.AMZN.WEB-DL.Hindi.DDP5.1-English.DDP5.1.HDR.H.265-4kHdHub.Com.mkv\n5.01 GB",
            "url": "https://pixeldrain.net/api/file/2Qw6G3Sk",
            "quality": "2160p",
            "size": "5.01 GB",
            "fileName": "Harlem.S01E03.Rainbow.Sprinkles.2160p.AMZN.WEB-DL.Hindi.DDP5.1-English.DDP5.1.HDR.H.265-4kHdHub.Com.mkv",
            "type": "direct",
            "behaviorHints": {
              "bingeGroup": "4khdhub-streams"
            }
          },
          {
            "name": "4KHDHub - Pixeldrain - 1080p",
            "title": "Harlem.S01E03.1080p.AMZN.WEB-DL.Hindi.DDP5.1-English.DDP5.1.H.264-4kHdHub.Com.mkv\n2.27 GB",
            "url": "https://pixeldrain.dev/api/file/FhX8xYps?download",
            "quality": "1080p",
            "size": "2.27 GB",
            "fileName": "Harlem.S01E03.1080p.AMZN.WEB-DL.Hindi.DDP5.1-English.DDP5.1.H.264-4kHdHub.Com.mkv",
            "type": "direct",
            "behaviorHints": {
              "bingeGroup": "4khdhub-streams"
            }
          }
        ],
        "count": 3
      }
    },
    {
      "key": "prov:4khdhub:tv:85077:s3e3",
      "storedAt": 1757793712314,
      "meta": {
        "storedAt": 1757793712,
        "urlCount": 2,
        "ttlSeconds": 0
      },
      "data": {
        "success": true,
        "provider": "4khdhub",
        "type": "tv",
        "tmdbId": "85077",
        "imdbId": "tt5622316",
        "season": 3,
        "episode": 3,
        "streams": [
          {
            "name": "4KHDHub - Pixeldrain - 1080p",
            "title": "The.Chosen.S03E03.Physician.Heal.Yourself.1080p.NF.WEB-DL.Hindi.DDP5.1-English.DDP5.1.H.264-4kHdHub.Com.mkv\n3.24 GB",
            "url": "https://pixeldrain.net/api/file/YrBJb6Vp",
            "quality": "1080p",
            "size": "3.24 GB",
            "fileName": "The.Chosen.S03E03.Physician.Heal.Yourself.1080p.NF.WEB-DL.Hindi.DDP5.1-English.DDP5.1.H.264-4kHdHub.Com.mkv",
            "type": "direct",
            "behaviorHints": {
              "bingeGroup": "4khdhub-streams"
            }
          },
          {
            "name": "4KHDHub - FSL Server - 1080p",
            "title": "The.Chosen.S03E03.Physician.Heal.Yourself.1080p.NF.WEB-DL.Hindi.DDP5.1-English.DDP5.1.H.264-4kHdHub.Com.mkv\n3.24 GB",
            "url": "https://fsl.fastcloud.casa/The.Chosen.S03E03.Physician.Heal.Yourself.1080p.NF.WEB-DL.Hindi.DDP5.1-English.DDP5.1.H.264-4kHdHub.Com.mkv?token=1757793699",
            "quality": "1080p",
            "size": "3.24 GB",
            "fileName": "The.Chosen.S03E03.Physician.Heal.Yourself.1080p.NF.WEB-DL.Hindi.DDP5.1-English.DDP5.1.H.264-4kHdHub.Com.mkv",
            "type": "direct",
            "behaviorHints": {
              "bingeGroup": "4khdhub-streams"
            }
          }
        ],
        "count": 2
      }
    },
    {
      "key": "prov:dahmermovies:tv:85077:s3e3",
      "storedAt": 1757793714717,
      "meta": {
        "storedAt": 1757793714,
        "urlCount": 1,
        "ttlSeconds": 0
      },
      "data": {
        "success": true,
        "provider": "dahmermovies",
        "type": "tv",
        "tmdbId": "85077",
        "imdbId": "tt5622316",
        "season": 3,
        "episode": 3,
        "streams": [
          {
            "name": "DahmerMovies",
            "title": "DahmerMovies Remux][AC3 5 1][AVC]-SiCFoI",
            "url": "https://a.111477.xyz/tvs/The%20Chosen/Season%203/The%20Chosen%20(2019)%20-%20S03E03%20-%20Physician%20Heal%20Yourself%20[Bluray-1080p%20Remux][AC3%205.1][AVC]-SiCFoI.mkv",
            "quality": "1080p | REMUX",
            "size": null,
            "type": "direct",
            "filename": "The Chosen (2019) - S03E03 - Physician Heal Yourself [Bluray-1080p Remux][AC3 5.1][AVC]-SiCFoI.mkv"
          }
        ],
        "count": 1
      }
    }
  ],
  "exportInfo": {
    "exportedAt": "2025-09-13T20:03:09.905Z",
    "totalOriginalEntries": 34,
    "newItemsInThisBatch": 34,
    "format": "compact_v1"
  }
}