{
  "originalCacheEntries": [
    {
      "key": "prov:dahmermovies:tv:1685:s21e8",
      "storedAt": 1757779122990,
      "meta": {
        "storedAt": 1757779122,
        "urlCount": 0,
        "ttlSeconds": 86400
      },
      "data": {
        "success": false,
        "provider": "dahmermovies",
        "type": "tv",
        "tmdbId": "1685",
        "imdbId": "tt0437741",
        "season": 21,
        "episode": 8,
        "streams": [],
        "count": 0
      }
    },
    {
      "key": "prov:dvdplay:tv:1685:s21e8",
      "storedAt": 1757779121152,
      "meta": {
        "storedAt": 1757779121,
        "urlCount": 0,
        "ttlSeconds": 86400
      },
      "data": {
        "success": false,
        "provider": "dvdplay",
        "type": "tv",
        "tmdbId": "1685",
        "imdbId": "tt0437741",
        "season": 21,
        "episode": 8,
        "streams": [],
        "count": 0
      }
    },
    {
      "key": "prov:4khdhub:tv:2004:s5e21",
      "storedAt": 1757779140579,
      "meta": {
        "storedAt": 1757779140,
        "urlCount": 0,
        "ttlSeconds": 86400
      },
      "data": {
        "success": false,
        "provider": "4khdhub",
        "type": "tv",
        "tmdbId": "2004",
        "imdbId": "tt0212671",
        "season": 5,
        "episode": 21,
        "streams": [],
        "count": 0
      }
    },
    {
      "key": "prov:dvdplay:tv:2004:s5e21",
      "storedAt": 1757779142110,
      "meta": {
        "storedAt": 1757779142,
        "urlCount": 0,
        "ttlSeconds": 86400
      },
      "data": {
        "success": false,
        "provider": "dvdplay",
        "type": "tv",
        "tmdbId": "2004",
        "imdbId": "tt0212671",
        "season": 5,
        "episode": 21,
        "streams": [],
        "count": 0
      }
    },
    {
      "key": "prov:uhdmovies:tv:2004:s5e21",
      "storedAt": 1757779141588,
      "meta": {
        "storedAt": 1757779141,
        "urlCount": 0,
        "ttlSeconds": 86400
      },
      "data": {
        "success": false,
        "provider": "uhdmovies",
        "type": "tv",
        "tmdbId": "2004",
        "imdbId": "tt0212671",
        "season": 5,
        "episode": 21,
        "streams": [],
        "count": 0
      }
    },
    {
      "key": "prov:dahmermovies:tv:43775:s1e4",
      "storedAt": 1757779138024,
      "meta": {
        "storedAt": 1757779138,
        "urlCount": 1,
        "ttlSeconds": 0
      },
      "data": {
        "success": true,
        "provider": "dahmermovies",
        "type": "tv",
        "tmdbId": "43775",
        "imdbId": "tt2222135",
        "season": 1,
        "episode": 4,
        "streams": [
          {
            "name": "DahmerMovies",
            "title": "DahmerMovies ][8bit][h264][EAC3 5 1]-NTb",
            "url": "https://a.111477.xyz/tvs/Dog%20with%20a%20Blog/Season%201/Dog%20with%20a%20Blog%20(2012)%20-%20S01E04%20-%20Wingstan%20[WEBDL-1080p][8bit][h264][EAC3%205.1]-NTb.mkv",
            "quality": "1080p",
            "size": null,
            "type": "direct",
            "filename": "Dog with a Blog (2012) - S01E04 - Wingstan [WEBDL-1080p][8bit][h264][EAC3 5.1]-NTb.mkv"
          }
        ],
        "count": 1
      }
    },
    {
      "key": "prov:dahmermovies:tv:64836:s1e3",
      "storedAt": 1757779123208,
      "meta": {
        "storedAt": 1757779123,
        "urlCount": 0,
        "ttlSeconds": 86400
      },
      "data": {
        "success": false,
        "provider": "dahmermovies",
        "type": "tv",
        "tmdbId": "64836",
        "imdbId": "tt4855114",
        "season": 1,
        "episode": 3,
        "streams": [],
        "count": 0
      }
    },
    {
      "key": "prov:dvdplay:tv:64836:s1e3",
      "storedAt": 1757779121151,
      "meta": {
        "storedAt": 1757779121,
        "urlCount": 0,
        "ttlSeconds": 86400
      },
      "data": {
        "success": false,
        "provider": "dvdplay",
        "type": "tv",
        "tmdbId": "64836",
        "imdbId": "tt4855114",
        "season": 1,
        "episode": 3,
        "streams": [],
        "count": 0
      }
    },
    {
      "key": "prov:dahmermovies:tv:87917:s2e1",
      "storedAt": 1757779130265,
      "meta": {
        "storedAt": 1757779130,
        "urlCount": 2,
        "ttlSeconds": 0
      },
      "data": {
        "success": true,
        "provider": "dahmermovies",
        "type": "tv",
        "tmdbId": "87917",
        "imdbId": "tt7772588",
        "season": 2,
        "episode": 1,
        "streams": [
          {
            "name": "DahmerMovies",
            "title": "DahmerMovies ][DV HDR10][EAC3 Atmos 5 1][HEVC]-SiC",
            "url": "https://a.111477.xyz/tvs/For%20All%20Mankind/Season%202/For%20All%20Mankind%20(2019)%20-%20S02E01%20-%20Every%20Little%20Thing%20[WEBDL-2160p][DV%20HDR10][EAC3%20Atmos%205.1][HEVC]-SiC.mkv",
            "quality": "2160p | DV | HDR",
            "size": null,
            "type": "direct",
            "filename": "For All Mankind (2019) - S02E01 - Every Little Thing [WEBDL-2160p][DV HDR10][EAC3 Atmos 5.1][HEVC]-SiC.mkv"
          },
          {
            "name": "DahmerMovies",
            "title": "DahmerMovies Remux][DTS-HD MA 5 1][AVC]-FraMeSToR",
            "url": "https://a.111477.xyz/tvs/For%20All%20Mankind/Season%202/For%20All%20Mankind%20(2019)%20-%20S02E01%20-%20Every%20Little%20Thing%20[Bluray-1080p%20Remux][DTS-HD%20MA%205.1][AVC]-FraMeSToR.mkv",
            "quality": "1080p | REMUX",
            "size": null,
            "type": "direct",
            "filename": "For All Mankind (2019) - S02E01 - Every Little Thing [Bluray-1080p Remux][DTS-HD MA 5.1][AVC]-FraMeSToR.mkv"
          }
        ],
        "count": 2
      }
    },
    {
      "key": "prov:moviesmod:tv:87917:s2e1",
      "storedAt": 1757779122162,
      "meta": {
        "storedAt": 1757779122,
        "urlCount": 2,
        "ttlSeconds": 0
      },
      "data": {
        "success": true,
        "provider": "moviesmod",
        "type": "tv",
        "tmdbId": "87917",
        "imdbId": "tt7772588",
        "season": 2,
        "episode": 1,
        "streams": [
          {
            "name": "MoviesMod",
            "title": "For All Mankind S02E01 1080p 10Bit English Esubs Moviesmod Mobi\n646.6MB • 10-bit",
            "url": "https://video-downloads.googleusercontent.com/ADGPM2nv9OwSZ9VtnmZN6NW4Npdz6WtIfOGxbODy6Kj_aEfyVtf5pZHVAuUcz8ZWY1D0E3DZUKkFAx4RTp6iSX_0XKhNzoo1zzVy-q84FaXOFEPIRQ7FKPXgFg2sD0dx77ak6NWFcI0vJ8YUJdbOtm0Lz99wEKbH_jqhDjzvPnY4WDOmJENXg6H0Dj0n2n42KKEf5a0L-lvIN3kk1l_AqiUj6z5soyhccstvoyepp7-RIo7Jktlt7xIVD7B2itAhrc5zYY9P8UfjjdLOYEJ63s38ME1b8iGm4MNUmpCpgmTR11CRfvYrStO0kT1Z9u7EVn-NpZDXtjygP9jNJJkkfSY6otVaomJ65Ih80D8MhoOI46i1sv7j-ghA1MJHIA2UQTa7y4qmh6ZoocKKbpWP4mU_O83d2Nx72k7_4JDvNCRj-O5Lph7a0LwOdMyKqtRzmjA6sX-RbPXx51x-PangBhBTdD0Je1eKspcDK0NVrJGirxGt5unvL2poBxINTAAuoaJRY-s2tSQ6lPn5qNLNFhqcCciDjE-qd10GR5jJ18hXdyP8CDxdMXMOM2lGLeXZaLaRLURpYmfkFMi9fENs4q9Y2tWl3gFPzr169juxPuQQGu0I_9q2Rbot2zQ-1ABP_ZTUsZ5-uXrAv-EebTPs8O65trJozmFN7qQHBkuCOSnduA-6uSRVHnagxfVjhpqaFe8UvyJUW29GeGS63rtMYqBk3_BXovmlbl1YLjbMZq4x93tatR8ybDJ1X3eEiVcikHWZcbAF-HIECh_Q01pCcubEyRGxvcoa_FEpeWUNgF2qL5-aUEnRIvxTHrD5UWwZLWs_CCNY8WLunJ536lzaMhC_CyPhoV75df0An4u_qsFh4R0ntAfuw_NYq_LXkpFfng3mPgPiBWtpgzNtNfGcLR5-tsB67gkDSBpDFqOBEhTxdD8aq7ho8_wR0pqU_sDUT4l5ntJRh8pnoSUdCHMPdKCfHlqfNS6RvLg7LbJSuqccBJRWerkjAQyULlC4r1ClUQP48lTIWwfSEda2_CJuMObsKKa7NR6MoHmF_Zs2xDrG0Xrr1Xv1dd8",
            "quality": "1080p",
            "size": "646.6MB",
            "fileName": "For.All.Mankind.S02E01.1080p.10Bit.English.Esubs.Moviesmod.Mobi.mkv",
            "type": "direct"
          },
          {
            "name": "MoviesMod",
            "title": "For All Mankind S02E01 720p 10Bit English Esubs Moviesmod Mobi\n272.59MB • 10-bit",
            "url": "https://video-downloads.googleusercontent.com/ADGPM2k532hS2FmV1Uv5YvJ4GDuUjGuC6LWHD-lbU3f9OB2UAzhu1HBv1qLKA865_WdNiCvXMmJmW7hn2FHieznfulZTFch99D3cALMwQev7GYEnKXGBkzZuDETd7B-dUlcJyJ58231GzEmiTgxGFlKQNI1oV1Sdk8C_aOUAwy9sP9v8KfNNoyHl2WtXgw1gnKFFVQEd_C1A0zd2-ss92QwVqiF8--noOt7C8mBlL-U-gmaE4yCo89bSgSTgDPpEoGJpZ1qXjYbCuumBLMKnRNPQ6RrOwhXsnxPbjKZlC4geOGpqhN1gYLI9_bqURJYAQhtub_7MEW2iSlWS1Hjewg9Yqqd7zcW15aVuZ1gcqWAH-Bbc6a-L-8KyrSzcAbWrinFA50aSCxYxrSdP3utqcGbfVNnA6nzIFr8udHu85BwVrGnxjE04-aYyChrbmQIrDGYm0xscc-UR4HGgmc5EJlNrhFplzMbd3T5RTMxWg1p0EXWcFMA_ifI4EHl8vVvH-6DmA5VLZFMvJ0aFtLWpMl9wJIsl_8t2aUQ5pvUXsXYs-Y4vbn7SBo8MxcoYk8zuCHIGUQPHBcdN1KQU0wsffyF7tPN8jpQUNukd0K-Ztfbt1Fk5yB9WfpP3-47V277usN1FXhkRp_UOutnOmT0TXrnZBG4CZHzoNUuBltn-jh6og89W4dl7CKdMRkLTObUJtWxW9GmoxPM0uLZtDjFVh9vKcYN8D5TTh2eyPiDD_yyzb48PQiYTE6UFh79K5rGwOVCrPyXyVPlkX7cpuj8AbwsTfSX-jyPD0VWgZByv3AklpG1HsKaw-GLYWlJNCpWzcdxSQsI8BZTY8MFFrMXfm6D_3-b6jytCL1fZTnnhlVFYp1-Slr7XnXWIsWINGh6iKR04jvT6tBshNrMpOwMosKUMzq8wY8isRb2Wz-VxzNjBSMr6kt_5Zui1Bt0U-pGVvYBi9-K3gcCCS3WPYWgcg_0hIXa7jHY-6uVYdsH_A7aB_ddKRS9Iz85d_wsY6qUZjvo9EcBRkOuoRatvqYsNMLtMPfSHD4x3shRIw5ebgv5GTMaOql5k25A",
            "quality": "720p",
            "size": "272.59MB",
            "fileName": "For.All.Mankind.S02E01.720p.10Bit.English.Esubs.Moviesmod.Mobi.mkv",
            "type": "direct"
          }
        ],
        "count": 2
      }
    }
  ],
  "exportInfo": {
    "exportedAt": "2025-09-13T15:59:02.112Z",
    "totalOriginalEntries": 10,
    "newItemsInThisBatch": 10,
    "format": "compact_v1"
  }
}